[

{


"id": "d273b26a-094d-43c6-b593-e9585a962ce9",


"name": "쎄라덤 비비 화이트 모이스춰",


"price": "34000",


"brand": "쎄라덤",


"image_url": "https://static.mynunc.com/ext/images/goods/top/22/01/14/06/BO00112821/0000256887.png",


"category": 5,


"site": 5,


"site_id": "BO00112821",


"link": "https://www.mynunc.com/product/goods/view-goods?goodsId=BO00112821&dspCateId=",


"site_category": "20000139",


"volume": "40g",


"expiration_date": "개봉 후 12개월 이내 사용 권장",


"usage": "본 품 적당량을 취해 피부에 골고루 펴 발라줍니다.",


"origin": "한국",


"ingredients": "정제수,사이클로펜타실록산,사이클로헥사실록산,부틸렌글라이콜,에칠헥실메톡시신나메이트,세틸피이지/피피지-10/1디메치콘,에칠헥실살리실레이트,티타늄디옥사이드,폴리메칠메타크릴레이트,나이아신아마이드,트리에톡시카프릴릴실란,스테아릭애씨드,페닐트리메치콘,소르비탄올리베이트,알루미늄하이드록사이드,오조케라이트,소듐클로라이드,디스테아디모늄헥토라이트,실리카,트리메칠실록시실리케이트,디메치콘,프로필렌카보네이트,인도키노나무껍질추출물,글리세린,하이드로제네이티드레시틴,카프릴릭/카프릭트리글리세라이드,페네칠알코올,토코페릴아세테이트,판테놀,마그네슘아스코빌포스페이트,레티닐팔미테이트,콜레스테롤,세라마이드3,잔탄검,1,2-헥산디올,알로에베라잎추출물,토코페롤,콩단백질,치옥틱애씨드,클로페네신,페녹시에탄올,디소듐이디티에이,흑색산화철,황색산화철,적색산화철",


"caution": "1) 화장품을 사용하여 다음과 같은 이상이 있는 경우네는 사용을 중지하여야 하며, 계속 사용하면 증상이 악화되므로 피부과 전문의 등에게 상담하십시오. 가) 사용 중 붉은 반점, 부어오름, 가려움증, 자극 등의 이상이 있는 경우 나) 적용 부위가 직사광선에 의하여 위와 같은 이상이 있는 경우 2) 상처가 있는 부위, 습진 및 피부염 등의 이상이 있는 부위에는 사용을 금하십시오. 3) 보관 및 취급 시의 주의사항 가) 사용 후에는 반드시 마개를 닫아주십시오."

},

{


"id": "f8b0a4eb-a190-4296-8220-e49c08da2fb1",


"name": "쎄라덤 오가 50 썬블럭",


"price": "31000",


"brand": "쎄라덤",


"image_url": "https://static.mynunc.com/ext/images/goods/top/22/01/14/06/BO00112821/0000256887.png",


"category": 5,


"site": 5,


"site_id": "BO00112806",


"link": "https://www.mynunc.com/product/goods/view-goods?goodsId=BO00112806&dspCateId=",


"site_category": "20000139",


"volume": "50g",


"expiration_date": "단상자 개별 기재",


"usage": "본 품 적당량을 취하여 피부에 골고루 펴 바른다.",


"origin": "한국",


"ingredients": "상세페이지 참조",


"caution": "1) 화장품 사용 시 또는 사용 후 직사광선에 의하여 사용부위가 붉은 반점, 부어오름 또는 가려움증 등의 이상 증상이나 부작용이 있는 경우 전문의 등과 상담할 것 2) 상처가 있는 부위 등에는 사용을 자제할 것 3) 보관 및 취급 시의 주의사항 가) 어린이의 손이 닿지 않는 곳에 보관할 것 나) 직사광선을 피해서 보관할 것 *만 3세 이하 어린이에게는 사용하지말 것\""

},

{


"id": "af2f50fe-7770-4a75-b64a-fe894d16b272",


"name": "DMS 더모 프로텍션 울트라 라이트 썬블록50g",


"price": "38000",


"brand": "DMS",


"image_url": "https://static.mynunc.com/ext/images/goods/top/22/01/14/06/BO00112821/0000256887.png",


"category": 5,


"site": 5,


"site_id": "BO00112804",


"link": "https://www.mynunc.com/product/goods/view-goods?goodsId=BO00112804&dspCateId=",


"site_category": "20000139",


"volume": "50g",


"expiration_date": "별도 표기",


"usage": "스킨케어 맨 마지막 단계 또는 메이크업 전에 얼굴과 목 등 자외선에 노출되기 쉬운 부위에 고르게 펴 발라줍니다.",


"origin": "한국",


"ingredients": "상세페이지 참조 ",


"caution": "1) 화장품 사용 시 또는 사용 후 직사광선에 의하여 사용부위가 붉은 반점, 부어오름 또는 가려움증 등의 이상 증상이나 부작용이 있는 경우 전문의 등과 상담할 것 2) 상처가 있는 부위 등에는 사용을 자제할 것 3) 보관 및 취급 시의 주의사항 가) 어린이의 손이 닿지 않는 곳에 보관할 것 나) 직사광선을 피해서 보관할 것 *만 3세 이하 어린이에게는 사용하지말 것\""

},

{


"id": "3b9e2e8f-f48e-4585-a189-f9ea8404c38d",


"name": "라포티셀 더 마일드 썬 프로텍션 50ml",


"price": "24000",


"brand": "라포티셀",


"image_url": "https://static.mynunc.com/ext/images/goods/top/22/01/14/06/BO00112821/0000256887.png",


"category": 5,


"site": 5,


"site_id": "BO00112763",


"link": "https://www.mynunc.com/product/goods/view-goods?goodsId=BO00112763&dspCateId=",


"site_category": "20000139",


"volume": "50",


"expiration_date": "2021년 5월 제조분부터 순차발송/ 개봉후 사용기한 12개월",


"usage": "아침, 기초 손질의 마지막 단계에 적당량을 취해 피부결을 따라 골고루 펴발라주세요.",


"origin": "한국",


"ingredients": "정제수, 사이클로메티콘, 징크옥사이드, 티타늄디옥사이드, 프로판다이올, 다이부틸아디페이트, 폴리글리세릴-3폴리다이메틸실록시에틸다이메티콘, 카프릴릴메티콘, 1,2-헥산다이올, 다이스테아다이모늄헥토라이트, 마그네슘설페이트, 하이드로젠다이메티콘, 알루미늄하이드록사이드, C30-45알킬세테아릴다이메티콘크로스폴리머, 폴리글리세릴-2다이폴리하이드록시스테아레이트, 스타이렌/아크릴레이트코폴리머, 스테아릭애씨드, 라벤더오일, 펜틸렌글라이콜, 에틸헥실글리세린, 옥틸도데칸올, 트라넥사믹애씨드, 다이포타슘글리시리제이트, 글리세린, 에키움 플란타기네움씨오일, 멕시칸치아씨추출물, 약모밀추출물, 병풀추출물, 부틸렌글라이콜, 쓴박하추출물, 프룩토올리고사카라이드, 사카라이드하이드롤리세이트, 풍선덩굴꽃/잎/덩굴추출물, 풀루란, 해바라기씨오일불검화물, 범부채뿌리추출물, 세틸에틸헥사노에이트, 솔비탄세스퀴올리에이트, 다이카프릴릴카보네이트, 시트릭애씨드, 토코페롤, 리날룰, 리모넨",


"caution": "1) 화장품 사용 시 또는 사용 후 직사광선에 의하여 사용부위가 붉은 반점, 부어오름 또는 가려움증 등의 이상 증상이나 부작용이 있는 경우 전문의 등과 상담할 것 2) 상처가 있는 부위 등에는 사용을 자제할 것 3) 보관 및 취급 시의 주의사항 가) 어린이의 손이 닿지 않는 곳에 보관할 것 나) 직사광선을 피해서 보관할 것"

},

{


"id": "4d534b23-37cf-4da9-b56a-462c9e9088ab",


"name": "라포티셀 내추럴 미네랄 선 프로텍션 50ml",


"price": "19200",


"brand": "라포티셀",


"image_url": "https://static.mynunc.com/ext/images/goods/top/22/01/14/06/BO00112821/0000256887.png",


"category": 5,


"site": 5,


"site_id": "BO00112584",


"link": "https://www.mynunc.com/product/goods/view-goods?goodsId=BO00112584&dspCateId=",


"site_category": "20000139",


"volume": "50",


"expiration_date": "개봉 후 12개월",


"usage": "상세페이지 참고",


"origin": "한국",


"ingredients": "정제수, 사이클로펜타실록세인, 징크옥사이드, 프로판다이올, 티타늄디옥사이드, 피이지-10다이메티콘, 다이메티콘, 사이클로메티콘, 다이스테아다이모늄헥토라이트, 펜틸렌글라이콜, 마그네슘설페이트, 멕시칸치아씨추출물, 병풀추출물, 약모밀추출물, 알루미늄하이드록사이드, 하이드로젠다이메티콘, 스테아릭애씨드, 다이메티콘크로스폴리머, 솔비탄세스퀴올리에이트, 페닐트라이메티콘, 프룩토올리고사카라이드, 사카라이드하이드롤리세이트, 풀루란, 1,2-헥산다이올, 에틸헥실글리세린, 옥틸도데칸올, 판테놀, 부틸렌글라이콜, 에키움 플란타기네움씨오일, 알로에베라잎추출물, 소듐하이알루로네이트, 풍선덩굴꽃/잎/덩굴추출물, 해바라기씨오일불검화물, 오레가노잎추출물, 편백잎추출물, 흰버드나무껍질추출물, 캐모마일꽃수, 락토바실러스/콩발효추출물, 쇠비름추출물, 육계나무껍질추출물, 황금추출물, 토코페롤, 페녹시에탄올, 향료",


"caution": "1) 화장품 사용 시 또는 사용 후 직사광선에 의하여 사용부위가 붉은 반점, 부어오름 또는 가려움증 등의 이상 증상이나 부작용이 있는 경우 전문의 등과 상담할 것 2) 상처가 있는 부위 등에는 사용을 자제할 것 3) 보관 및 취급 시의 주의사항 가) 어린이의 손이 닿지 않는 곳에 보관할 것 나) 직사광선을 피해서 보관할 것"

},

{


"id": "b77b653c-29a6-4703-ace3-0d5d0e9923f1",


"name": "NEW 시카딘 레스큐 마일드 선크림",


"price": "16000",


"brand": "미샤",


"image_url": "https://static.mynunc.com/ext/images/goods/top/22/01/14/06/BO00112821/0000256887.png",


"category": 5,


"site": 5,


"site_id": "BO00111915",


"link": "https://www.mynunc.com/product/goods/view-goods?goodsId=BO00111915&dspCateId=",


"site_category": "20000139",


"volume": "40",


"expiration_date": "발송일로부터 사용기한이 24개월 이상 남은 제품으로 발송",


"usage": "상세페이지 참조",


"origin": "한국",


"ingredients": "병풀추출물, 징크옥사이드, 사이클로헥사실록세인, 다이카프릴릴에터, 프로필헵틸카프릴레이트, 부틸옥틸살리실레이트, 티타늄디옥사이드, 카프릴릴메티콘, 프로판다이올, 폴리글리세릴-4다이아이소스테아레이트/폴리하이드록시스테아레이트/세바케이트, 아이소도데케인, 메틸메타크릴레이트크로스폴리머, 병풀뿌리추출물, 라벤더오일, 베르가모트오일, 로즈마리잎오일, 소듐하이알루로네이트, 캐모마일꽃오일, 하이드로제네이티드레시틴, 다이스테아다이모늄헥토라이트, 마그네슘설페이트, 스테아릭애씨드, 알루미늄하이드록사이드, 폴리글리세릴-3폴리다이메틸실록시에틸다이메티콘, 트라이에톡시카프릴릴실레인, 1,2-헥산다이올, 폴리메틸실세스퀴옥세인, 글리세릴카프릴레이트, 카프릴릴글라이콜, 에틸헥실글리세린, 칼슘알루미늄보로실리케이트, 칼라민, 정제수, 클로렐라 불가리스가루, 글리세린, 라피노오스, 펜틸렌글라이콜, 판테놀, 콜레스테롤, 세라마이드엔피, 트로메타민, 마데카소사이드, 마데카식애씨드, 아시아티코사이드, 아시아틱애씨드, 리날룰, 리모넨",


"caution": "1) 화장품 사용 시 또는 사용 후 직사광선에 의하여 사용부위가 붉은 반점, 부어오름 또는 가려움증 등의 이상 증상이나 부작용이 있는 경우 전문의 등과 상담할 것 2) 상처가 있는 부위 등에는 사용을 자제할 것 3) 보관 및 취급 시의 주의사항 가) 어린이의 손이 닿지 않는 곳에 보관할 것 나) 직사광선을 피해서 보관할 것"

},

{


"id": "7562be81-4c58-46fd-8c09-c8c3d5971425",


"name": "리얼베리어 시카릴리프 마일드 선플루이드 55ml",


"price": "15960",


"brand": "리얼베리어",


"image_url": "https://static.mynunc.com/ext/images/goods/top/22/01/14/06/BO00112821/0000256887.png",


"category": 5,


"site": 5,


"site_id": "BO00109492",


"link": "https://www.mynunc.com/product/goods/view-goods?goodsId=BO00109492&dspCateId=",


"site_category": "20000139",


"volume": "55",


"expiration_date": "24개월",


"usage": "사용 전 충분히 흔들어 준 후, 스킨케어 마지막 단계에서 적당량을 취해 피부결을 따라 꼼꼼하게 펴 발라줍니다.",


"origin": "한국",


"ingredients": "정제수, 징크옥사이드, 다이실록세인, 부틸렌글라이콜다이카프릴레이트/다이카프레이트, 프로필헵틸카프릴레이트, 다이카프릴릴에터, 티타늄디옥사이드, 부틸렌글라이콜, 메틸트라이메티콘, 칼라민, 광곽향오일, 연필향나무오일, 불가리스쑥오일, 페퍼민트오일, 병풀추출물, 폴리글리세릴-4다이아이소스테아레이트/폴리하이드록시스테아레이트/세바케이트, 스테아릭애씨드, 알루미늄하이드록사이드, 트라이에톡시카프릴릴실레인, 소듐클로라이드, 실리카, 폴리메틸실세스퀴옥세인, 1,2-헥산다이올, 글리세릴카프릴레이트, 카프릴릴글라이콜, 카프릴릭/카프릭트라이글리세라이드, 폴리글리세릴-3올리에이트, 에틸헥실글리세린, 디이소스테아로일폴리글리세릴-3다이머디리놀리에이트, 토코페롤, 미리스토일/팔미토일옥소스테아라마이드/아라카마이드엠이에이, 마데카소사이드, 알란토인, 판테놀, 마데카식애씨드, 아시아티코사이드, 아시아틱애씨드, 펜틸렌글라이콜",


"caution": "1. 화장품 사용 시 또는 사용 후 직사광선에 의하여 사용부위가 붉은 반점, 부어오름 또는 가려움증 등의 이상 증상이나 부작용이 있는 경우 전문의 등과 상담할 것 2. 상처가 있는 부위 등에는 사용을 자제할 것 3. 보관 및 취급 시의 주의 사항  가) 어린이의 손이 닿지 않는 곳에 보관할 것  나) 직사광선을 피해서 보관할 것"

},

{


"id": "85573417-4aea-4d33-ad73-0d258aadab29",


"name": "포니이펙트 프라임 프로텍트 선 커버 SPF40+ PA++ 40g",


"price": "9600",


"brand": "포니이펙트",


"image_url": "https://static.mynunc.com/ext/images/goods/top/22/01/14/06/BO00112821/0000256887.png",


"category": 5,


"site": 5,


"site_id": "BO00109404",


"link": "https://www.mynunc.com/product/goods/view-goods?goodsId=BO00109404&dspCateId=",


"site_category": "20000139",


"volume": "40g",


"expiration_date": "36개월",


"usage": "기초 스킨케어 후 적당량을 덜어 피부 결에 따라 골고루 펴 발라줍니다.",


"origin": "한국",


"ingredients": "[Ivory 001 아이보리] 정제수, 사이클로펜타실록세인, 티타늄디옥사이드 (CI 77891), 글리세린, 아이소에이코산, 아이소도데케인, 변성알코올, 메틸프로판다이올, 트라이메틸실록시실리케이트, 라우릴피이지-10트리스(트라이메틸실록시)실릴에틸다이메티콘, 다이메티콘, 카프릴릭/카프릭트라이글리세라이드, 나이아신아마이드, 펜틸렌글라이콜, 황색산화철 (CI 77492), 세틸피이지/피피지-10/1다이메티콘, 다이아이소스테아릴말레이트, 페닐트라이메티콘, 실리카, 합성플루오르플로고파이트, 다이스테아다이모늄헥토라이트, 피이지-9폴리다이메틸실록시에틸다이메티콘, 마그네슘설페이트, 트라이베헤닌, 스테아릭애씨드, 알루미나, 폴리프로필실세스퀴옥세인, 다이메티콘크로스폴리머, 트라이에톡시카프릴릴실레인, 알루미늄하이드록사이드, 에틸헥실글리세린, 바이오사카라이드검-1, 아데노신, 피이지-10다이메티콘, 다이소듐이디티에이, 페녹시에탄올, 향료, 적색산화철 (CI 77491), 흑색산화철 (CI 77499)향료, 알파-아이소메틸아이오논, 시트로넬올, 하이드록시시트로넬알, 리모넨, 리날룰  [Beige 002 베이지] 정제수, 사이클로펜타실록세인, 티타늄디옥사이드 (CI 77891), 글리세린, 아이소에이코산, 아이소도데케인, 변성알코올, 메틸프로판다이올, 트라이메틸실록시실리케이트, 라우릴피이지-10트리스(트라이메틸실록시)실릴에틸다이메티콘, 다이메티콘, 카프릴릭/카프릭트라이글리세라이드, 나이아신아마이드, 펜틸렌글라이콜, 황색산화철 (CI 77492), 세틸피이지/피피지-10/1다이메티콘, 다이아이소스테아릴말레이트, 페닐트라이메티콘, 실리카, 합성플루오르플로고파이트, 다이스테아다이모늄헥토라이트, 피이지-9폴리다이메틸실록시에틸다이메티콘, 마그네슘설페이트, 트라이베헤닌, 스테아릭애씨드, 알루미나, 폴리프로필실세스퀴옥세인, 다이메티콘크로스폴리머, 트라이에톡시카프릴릴실레인, 알루미늄하이드록사이드, 에틸헥실글리세린, 바이오사카라이드검-1, 아데노신, 피이지-10다이메티콘, 다이소듐이디티에이, 페녹시에탄올, 향료, 적색산화철 (CI 77491), 흑색산화철 (CI 77499)향료, 알파-아이소메틸아이오논, 시트로넬올, 하이드록시시트로넬알, 리모넨, 리날룰",


"caution": "1. 화장품 사용 시 또는 사용 후 직사광선에 의하여 사용부위가 붉은 반점, 부어오름 또는 가려움증 등의 이상 증상이나 부작용이 있는 경우 전문의 등과 상담할 것 2. 상처가 있는 부위 등에는 사용을 자제할 것 3. 보관 및 취급 시의 주의사항 1)어린이의 손이 닿지 않는 곳에 보관할 것 2)직사광선을 피해서 보관할 것"

},

{


"id": "f7066563-11c4-423e-be1d-b753a28519cb",


"name": "포니이펙트 프라임 프로텍트 선 베이스 SPF50+ PA++++ 50ml",


"price": "13200",


"brand": "포니이펙트",


"image_url": "https://static.mynunc.com/ext/images/goods/top/22/01/14/06/BO00112821/0000256887.png",


"category": 5,


"site": 5,


"site_id": "BO00109401",


"link": "https://www.mynunc.com/product/goods/view-goods?goodsId=BO00109401&dspCateId=",


"site_category": "20000139",


"volume": "50",


"expiration_date": "24개월",


"usage": "메이크업 전 단계에서 적당량을 덜어 피부 결에 따라 골고루 펴 발라줍니다. 수정화장 시, 화장솜이나 티슈 등에 묻혀 가볍게 쓸어 얼룩진 베이스를 닦아내고 적당량을 덜어 톡톡 두드리듯 발라주면 자외선 차단은 물론 촉촉하고 매끈한 피부 표현을 도와줘요.",


"origin": "한국",


"ingredients": "정제수, 호모살레이트, 에칠헥실살리실레이트, 메칠메타크릴레이트크로스폴리머, 변성알코올, 디프로필렌글라이콜, 부틸메톡시디벤조일메탄, 비스-에칠헥실옥시페놀메톡시페닐트리아진, 옥토크릴렌, 이소아밀p-메톡시신나메이트, 연꽃추출물, 백년초열매추출물, 마데카소사이드, 병풀추출물, 부틸렌글라이콜, 에탄올, 폴리소르베이트20, 소듐하이알루로네이트, 왕대수액, 자작나무수액, 편백수, 알로에베라잎추출물, 다마스크장미꽃수, 메톡시피이지/피피지-25/4디메치콘, 비스-피이지/피피지- 20/5피이지/피피지-20/5디메치콘, 카프릴릭/카프릭트리글리세라이드, 디메치콘, 아크릴레이트/C10-30알킬아크릴레이트크로스폴리머, 소듐아크릴레이트/소듐아크릴로일디메칠타우레이트코폴리머, 이소헥사데칸, 비에이치티, 소듐하이드록사이드, 폴리소르베이트80, 소르비탄올리에이트, 디소듐이디티에이, 카프릴릴글라이콜, 에칠헥실글리세린, 1,2-헥산디올, 향료",


"caution": "1. 화장품 사용 시 또는 사용 후 직사광선에 의하여 사용부위가 붉은 반점, 부어오름 또는 가려움증 등의 이상 증상이나 부작용이 있는 경우 전문의 등과 상담할 것 2. 상처가 있는 부위 등에는 사용을 자제할 것 3. 보관 및 취급 시의 주의사항 1) 어린이의 손이 닿지 않는 곳에 보관할 것 2) 직사광선을 피해서 보관할 것"

},

{


"id": "5668150c-7ede-4dcb-9f11-32bad018b898",


"name": "로레알파리 유브이 퍼펙트 30ml",


"price": "15750",


"brand": "로레알 파리",


"image_url": "https://static.mynunc.com/ext/images/goods/top/22/01/14/06/BO00112821/0000256887.png",


"category": 5,


"site": 5,


"site_id": "BO00106535",


"link": "https://www.mynunc.com/product/goods/view-goods?goodsId=BO00106535&dspCateId=",


"site_category": "20000139",


"volume": "30ml\r\n",


"expiration_date": "30개월",


"usage": "본 품 적당량을 취해 피부에 골고루 펴 바른다 ",


"origin": "중국 ",


"ingredients": "정제수 에칠헥실메톡시신나메이트 드로메트리졸트리실록산 글리세린 프로필렌글라이콜 디메치콘 티타늄디옥사이드 테레프탈릴리덴디캠퍼설포닉애씨드 디에칠아미노하이드록시벤조일헥실벤조에이트 트리에탄올아민 비스-에칠헥실옥시페놀메톡시페닐트리아진 스테아릭애씨드 포타슘세틸포스페이트 울트라마린 적색223호 아스코빌글루코사이드 토코페롤 소듐코코일사코시네이트 소듐시트레이트 페녹시에탄올 피이지-100스테아레이트 에칠파라벤 팔미틱애씨드 폴리글리세릴-4이소스테아레이트 리모넨 만니톨 잔탄검 리날룰 벤질알코올 트로메타민 이소프로필티타늄트리이소스테아레이트 카프릴릴글라이콜 카보머 제라니올 디소듐이디티에이 세틸알코올 메칠파라벤 부틸렌글라이콜 세틸디메치콘 부틸페닐메칠프로피오날 쉐어버터씨드케이크추출물 비트레오실라발효물 시트로넬올 알루미늄하이드록사이드 헥실라우레이트 헥실신남알 글리세릴스테아레이트 향료 ",


"caution": "1. 화장품을 사용하여 다음과 같이 이상이 있을 경우에는 사용을 중지할 것이며, 계속 사용하면 증상을 악화시키므로 피부과 전문의 등에게 상담할 것 1) 사용중 붉은 반점, 부어오름, 가려움증, 자극 등의 이상이 있을 경우 2) 적용부위가 직사광선에 의해 위와 같은 이상이 있을 경우2. 상처가 있는 곳 또는 습진 및 피부염등의 이상이 있는 부위에는 사용을 금할 것3. 눈 주위를 피해서 사용할 것4. 보관 및 취급상의 주의사항 1) 사용후에는 반드시 마개를 닫아둘 것 2) 유.소아의 손에 닿지 않는 곳에 보관할 것 25) 고온 내지 저온의 장소 및 일광이 닿는 곳에는 보관하지 말 것 "

},

{


"id": "7cdcf7d4-04fb-4c19-b8da-5ec3eb24d929",


"name": "에어리 페어리 선 프로텍터 50ml",


"price": "14560",


"brand": "지니브로",


"image_url": "https://static.mynunc.com/ext/images/goods/top/22/01/14/06/BO00112821/0000256887.png",


"category": 5,


"site": 5,


"site_id": "BO00105287",


"link": "https://www.mynunc.com/product/goods/view-goods?goodsId=BO00105287&dspCateId=",


"site_category": "20000139",


"volume": "50",


"expiration_date": "24개월/개봉후 12개월",


"usage": "상세페이지 참조",


"origin": "한국 ",


"ingredients": "상세페이지 참조",


"caution": "상세페이지 참조"

},

{


"id": "9d136f78-6a52-41f8-a24d-ed0fe07f2fa9",


"name": "올-오버 선 크림 60ml",


"price": "17160",


"brand": "포레마스트",


"image_url": "https://static.mynunc.com/ext/images/goods/top/22/01/14/06/BO00112821/0000256887.png",


"category": 5,


"site": 5,


"site_id": "BO00105294",


"link": "https://www.mynunc.com/product/goods/view-goods?goodsId=BO00105294&dspCateId=",


"site_category": "20000139",


"volume": "60",


"expiration_date": "24개월/개봉후 12개월",


"usage": "상세페이지 참조",


"origin": "한국 ",


"ingredients": "상세페이지 참조",


"caution": "상세페이지 참조"

},

{


"id": "4f584468-a76b-49e5-ab16-7dc7bc74acdf",


"name": "UV 퍼펙트 킬 선크림 50ml",


"price": "11760",


"brand": "데일리시",


"image_url": "https://static.mynunc.com/ext/images/goods/top/22/01/14/06/BO00112821/0000256887.png",


"category": 5,


"site": 5,


"site_id": "BO00105227",


"link": "https://www.mynunc.com/product/goods/view-goods?goodsId=BO00105227&dspCateId=",


"site_category": "20000139",


"volume": "50",


"expiration_date": "발송일로부터 사용기한이 18개월 남은 제품으로 발송",


"usage": "1 세안후스킨케어 마지막 단계에서 본품 적당량을 취해 자외선이 노출되기 쉬운 부위에 골고루 펴 바릅니다. 평상시 실내 활동시에 발라주셔도 좋습니다.",


"origin": "한국",


"ingredients": "정제수, 다이프로필렌글라이콜,C12-15알킬벤조에이트,하이드로제네이티드폴리데센, 디에칠아미노하이드록시벤조일헥실벤조에이트,징크옥사이드,에칠헥실메톡시신나메이트, 폴리글리세릴-3메틸글루코오스다이스테아레이트,다이메티콘,사이클로펜타실록세인, 스테아릭애씨드,세테아릴알코올,글리세린, 폴리솔베이트60,비스-에칠헥실옥시페놀 메톡시페닐트리아진, 에칠헥실살리실레이트,티타늄디옥사이드,부틸렌글라이콜,판테놀, 나무잎수술물,해수, 뽕나무껍질추출물,보리잎추출물, 들깨잎추출물 서양채싸大초무 글리세릴스테아레이트, 피이지-100스테아레이트,트라이에톡시카프릴릴실레인, 알루미늄하이드록사이드, 폴리아크릴레이트-13,폴리아이소부텐,폴리솔베이트20, 솔비탄아이소스테아레이트, 실리카,소듐폴리아크릴로일다이메틸타우레이트, 카프릴릴글라이콜,1,2-헥산다이올, 클로페네신, 다이소듐이디티에이,비에이치티,향료",


"caution": "1) 화장품 사용 시 또는 사용 후 직사광선에 의하여 사용부위가 붉은 반점, 부어오름 또는 가려움증 등의 이상 증상이나 부작용이 있는 경우 전문의 등과 상담할 것 2) 상처가 있는 부위 등에는 사용을 자제할 것 3) 보관 및 취급 시의 주의사항    가) 어린이의 손이 닿지 않는 곳에 보관할 것    나) 직사광선을 피해서 보관할 것 4) 알갱이가 눈에 들어갔을 때에는 물로 씻어내고, 이상이 있는 경우에는 전문의와 상담할 "

},

{


"id": "aae78b73-6b91-4ae2-9108-a747d321b7a1",


"name": "셀라피 에이징 쉴드 선크림 20ml",


"price": "14900",


"brand": "셀라피",


"image_url": "https://static.mynunc.com/ext/images/goods/top/22/01/14/06/BO00112821/0000256887.png",


"category": 5,


"site": 5,


"site_id": "BO00104650",


"link": "https://www.mynunc.com/product/goods/view-goods?goodsId=BO00104650&dspCateId=",


"site_category": "20000139",


"volume": "20",


"expiration_date": "36개월 (개봉 후 12개월)",


"usage": "스킨케어 마지막 단계에서 본품 적당량을 덜어 피부에 고르게 펴 발라 흡수시켜 줍니다. ",


"origin": "대한민국",


"ingredients": "정제수, 사이클로헥사실록세인, 징크옥사이드, 티타늄디옥사이드, 프로판다이올, 폴리글리세릴-3폴리다이메틸실록시에틸다이메티콘, 다이부틸아디페이트, 카프릴릴메티콘, 1,2-헥산다이올, 다이스테아다이모늄헥토라이트, 솔비탄세스퀴올리에이트, 마그네슘설페이트,  하이드로젠다이메티콘, 알루미늄하이드록사이드, C30-45알킬세테아릴다이메티콘크로스폴리머, 스테아릭애씨드, 오렌지껍질오일, 이노시톨, 에틸헥실글리세린, 옥틸도데칸올, 베르가모트오일, 글리세린, 부틸렌글라이콜, 라벤더오일, 리씨열매오일, 판테놀,  에키움 플란타기네움씨오일, 센티드제라늄오일, 바질오일, 티트리잎추출물, 사우수레아인볼루크라타추출물, 병풀추출물, 슬리퍼우드잎추출물, 카프릴릭/카프릭트라이글리세라이드, 하이드로제네이티드레시틴, 풍선덩굴꽃/잎/덩굴추출물, 해바라기씨오일불검화물,  하이드록시데실유비퀴논, 크랜베리추출물, 라즈베리추출물, 블랙체리열매추출물, 산수유열매추출물, 석류추출물, 다이카프릴릴카보네이트, 세틸에틸헥사노에이트, 폴리글리세릴-2다이폴리하이드록시스테아레이트, 토코페롤, 효모/자일리눔/홍차발효물, 리모넨, 리날룰, 시트랄, 시트로넬올",


"caution": "1. 화장품 사용 시 또는 사용 후 직사광선에 의하여 사용 부위가 붉은 반점, 부어오름 또는 가려움증 등의 이상 증상이나 부작용이 있는 경우 전문의 등과 상담할 것 2. 상처가 있는 부위 등에는 사용을 자제할 것 3. 보관 및 취급시의 주의사항 1) 어린이의 손이 닿지 않는 곳에 보관할 것 2) 직사광선을 피해서 보관할 것"

},

{


"id": "e77ced4c-697e-4c73-b36d-9095df59fceb",


"name": "에이징 쉴드 선크림 50ml",


"price": "28000",


"brand": "셀라피",


"image_url": "https://static.mynunc.com/ext/images/goods/top/22/01/14/06/BO00112821/0000256887.png",


"category": 5,


"site": 5,


"site_id": "BO00104649",


"link": "https://www.mynunc.com/product/goods/view-goods?goodsId=BO00104649&dspCateId=",


"site_category": "20000139",


"volume": "50",


"expiration_date": "36개월 (개봉 후 12개월)",


"usage": "스킨케어 마지막 단계에서 본품 적당량을 덜어 피부에 고르게 펴 발라 흡수시켜 줍니다. ",


"origin": "대한민국",


"ingredients": "정제수, 사이클로헥사실록세인, 징크옥사이드, 티타늄디옥사이드, 프로판다이올, 폴리글리세릴-3폴리다이메틸실록시에틸다이메티콘, 다이부틸아디페이트, 카프릴릴메티콘, 1,2-헥산다이올, 다이스테아다이모늄헥토라이트, 솔비탄세스퀴올리에이트, 마그네슘설페이트,  하이드로젠다이메티콘, 알루미늄하이드록사이드, C30-45알킬세테아릴다이메티콘크로스폴리머, 스테아릭애씨드, 오렌지껍질오일, 이노시톨, 에틸헥실글리세린, 옥틸도데칸올, 베르가모트오일, 글리세린, 부틸렌글라이콜, 라벤더오일, 리씨열매오일, 판테놀,  에키움 플란타기네움씨오일, 센티드제라늄오일, 바질오일, 티트리잎추출물, 사우수레아인볼루크라타추출물, 병풀추출물, 슬리퍼우드잎추출물, 카프릴릭/카프릭트라이글리세라이드, 하이드로제네이티드레시틴, 풍선덩굴꽃/잎/덩굴추출물, 해바라기씨오일불검화물,  하이드록시데실유비퀴논, 크랜베리추출물, 라즈베리추출물, 블랙체리열매추출물, 산수유열매추출물, 석류추출물, 다이카프릴릴카보네이트, 세틸에틸헥사노에이트, 폴리글리세릴-2다이폴리하이드록시스테아레이트, 토코페롤, 효모/자일리눔/홍차발효물, 리모넨, 리날룰, 시트랄, 시트로넬올",


"caution": "1. 화장품 사용 시 또는 사용 후 직사광선에 의하여 사용 부위가 붉은 반점, 부어오름 또는 가려움증 등의 이상 증상이나 부작용이 있는 경우 전문의 등과 상담할 것 2. 상처가 있는 부위 등에는 사용을 자제할 것 3. 보관 및 취급시의 주의사항 1) 어린이의 손이 닿지 않는 곳에 보관할 것 2) 직사광선을 피해서 보관할 것"

},

{


"id": "e013096f-e255-4726-b97e-f7f7bacdc524",


"name": "써머즈 데일리 선 라이트 크림 50ml",


"price": "8360",


"brand": "배럴",


"image_url": "https://static.mynunc.com/ext/images/goods/top/22/01/14/06/BO00112821/0000256887.png",


"category": 5,


"site": 5,


"site_id": "BO00104481",


"link": "https://www.mynunc.com/product/goods/view-goods?goodsId=BO00104481&dspCateId=",


"site_category": "20000139",


"volume": "50",


"expiration_date": "36개월",


"usage": "본품 적당량을 취해 피부에 골고루 펴 바른다",


"origin": "한국",


"ingredients": "정제수, 징크옥사이드, 사이클로펜타실록세인, 호모살레이트, 다이프로필렌글라이콜, 코코-카프릴레이트/카프레이트, 에칠헥실살리실레이트, 티타늄디옥사이드, 카프릴릴메티콘, 라우릴피이지-10트리스(트라이메틸실록시)실릴에틸다이메티콘, 나이아신아마이드, 다이스테아다이모늄헥토라이트, 마그네슘설페이트, 다이메티콘, 비닐다이메티콘/메티콘실세스퀴옥세인크로스폴리머, 1,2-헥산다이올, 메틸메타크릴레이트크로스폴리머, 트라이에톡시카프릴릴실레인, 스테아릭애씨드, 알루미늄하이드록사이드, 다이메티콘/피이지-10/15크로스폴리머, 글리세릴카프릴레이트, 다이메티콘/비닐다이메티콘크로스폴리머, 카프릴릴글라이콜, 다이카프릴릴카보네이트, 마이카, 에틸헥실글리세린, 아데노신, 소듐시트레이트, 토코페롤, 마데카소사이드, 칼라민, 판테놀, 향료, 적색산화철, 황색산화철",


"caution": "1. 화장품 사용 시 또는 사용 후 직사광선에 의하여 사용부위가 붉은 반점, 부어오름 또는 가려움증 등의 이상 증상 이나 부작용이 있는 경우 전문의 등과 상담할 것 2. 상처가 있는 부위 등에는 사용을 자제할 것 3. 보관 및 취급시의 주의사항 가. 어린이의 손이 닿지 않는 곳에 보관할 것 나. 직사광선을 피해서 보관할 것"

},

{


"id": "79901351-ad73-49b9-acbc-eb13721317e2",


"name": "써머즈 퍼펙트 선 쉴드 50ml",


"price": "8170",


"brand": "배럴",


"image_url": "https://static.mynunc.com/ext/images/goods/top/22/01/14/06/BO00112821/0000256887.png",


"category": 5,


"site": 5,


"site_id": "BO00104477",


"link": "https://www.mynunc.com/product/goods/view-goods?goodsId=BO00104477&dspCateId=",


"site_category": "20000139",


"volume": "50",


"expiration_date": "36개월",


"usage": "본품 적당량을 취해 피부에 골고루 펴 바른다",


"origin": "한국",


"ingredients": "정제수, 징크옥사이드, 다이부틸아디페이트, 프로필헵틸카프릴레이트, 사이클로헥사실록세인, 다이실록세인, 부틸렌글라이콜, 폴리글리세릴-5폴리리시놀리에이트, 나이아신아마이드, 메틸트라이메티콘, 카프릴릴메티콘, 다이스테아다이모늄헥토라이트, 디에칠아미노하이드록시벤조일헥실벤조에이트, 비스-에칠헥실옥시페놀메톡시페닐트리아진, 에칠헥실트리아존, 폴리메틸실세스퀴옥세인, 드럼스틱씨추출물, 캐모마일꽃추출물, 수염틸란드시아추출물, 병풀추출물, 풍선덩굴꽃/잎/덩굴추출물, 꿀풀추출물, 블래더랙추출물, 쌀겨오일, 에키움 플란타기네움씨오일, 티타늄디옥사이드, 마그네슘설페이트, 트라이에톡시카프릴릴실레인, 1,2-헥산다이올, 칼슘알루미늄보로실리케이트, 폴리글리세릴-3폴리다이메틸실록시에틸다이메티콘, 비닐다이메티콘/메티콘실세스퀴옥세인크로스폴리머, 카프릴릴글라이콜, 글리세릴카프릴레이트, 합성플루오르플로고파이트, 에틸헥실글리세린, 아데노신, 바이오사카라이드검-1, 토코페롤, 마데카소사이드, 카르노신, 옥틸도데칸올, 판테놀, 말토덱스트린, 프로필렌글라이콜, 칼라민, 해바라기씨오일불검화물, 트로폴론, 향료",


"caution": "1. 화장품 사용 시 또는 사용 후 직사광선에 의하여 사용부위가 붉은 반점, 부어오름 또는 가려움증 등의 이상 증상 이나 부작용이 있는 경우 전문의 등과 상담할 것 2. 상처가 있는 부위 등에는 사용을 자제할 것 3. 보관 및 취급시의 주의사항 가. 어린이의 손이 닿지 않는 곳에 보관할 것 나. 직사광선을 피해서 보관할 것"

},

{


"id": "4208bb39-11a8-4c48-8f84-70a6947ee78c",


"name": "프레스티지 선 데스까르고 50ml",


"price": "9900",


"brand": "잇츠스킨",


"image_url": "https://static.mynunc.com/ext/images/goods/top/22/01/14/06/BO00112821/0000256887.png",


"category": 5,


"site": 5,


"site_id": "BO00104350",


"link": "https://www.mynunc.com/product/goods/view-goods?goodsId=BO00104350&dspCateId=",


"site_category": "20000139",


"volume": "50",


"expiration_date": "30개월",


"usage": "적당량을 덜어 피부결에 따라 부드럽게 펴 바르고 가볍게 두드리며 흡수시켜 줍니다. 자외선에 노출되는 얼굴 및 몸에 수시로 덧발라 사용해 줍니다.",


"origin": "대한민국",


"ingredients": "정제수, 달팽이점액여과물, 에칠헥실메톡시신나메이트, 사이클로펜타실록세인, 카프릴릭/카프릭트라이글리세라이드, 옥토크릴렌, 변성알코올, 폴리메틸실세스퀴옥세인, 비스-에칠헥실옥시페놀메톡시페닐트리아진, 세테아릴알코올, 나이아신아마이드, 다이카프릴릴카보네이트, 디에칠아미노하이드록시벤조일헥실벤조에이트, 페닐벤즈이미다졸설포닉애씨드, C12-15알킬벤조에이트, 트라이에탄올아민, 폴리실리콘-15, 스테아릭애씨드, 송이버섯추출물, 해수, 프리클리페어열매추출물, 맥아추출물, 아데노신, 슈도알테로모나스발효추출물, 갈바눔수지오일, 다마스크장미꽃오일, 대왕송오일, 레몬껍질오일, 자몽씨오일, 캐모마일꽃오일, 아세틸헥사펩타이드-8, 글리세레스-26, 글리세릴스테아레이트, 피이지-100스테아레이트, 다이메티콘/비닐다이메티콘크로스폴리머, 솔비탄스테아레이트, 폴리솔베이트60, 폴리아크릴레이트-13, 에틸헥산다이올, 폴리아이소부텐, 글리세릴카프릴레이트, 잔탄검, 폴리솔베이트20, 다이메티콘, 글리세린, 카라멜, 다이소",


"caution": "1. 화장품 사용 시 또는 사용 후 직사광선에 의하여 사용부위가 붉은 반점, 부어오름 또는 가려움증 등의 이상 증상이나 부작용이 있는 경우 전문의 등과 상담할 것 2. 상처가 있는 부위 등에는 사용을 자제할 것 3. 보관 및 취급 시의 주의사항 가. 어린이의 손이 닿지 않는 곳에 보관할 것 나. 직사광선을 피해서 보관할 것"

},

{


"id": "c660ffaf-0770-4eeb-93a8-5e71891c5645",


"name": "더 레이아웃 마일드 선 플루이드 60ml",


"price": "8010",


"brand": "RNW",


"image_url": "https://static.mynunc.com/ext/images/goods/top/22/01/14/06/BO00112821/0000256887.png",


"category": 5,


"site": 5,


"site_id": "BO00102395",


"link": "https://www.mynunc.com/product/goods/view-goods?goodsId=BO00102395&dspCateId=",


"site_category": "20000139",


"volume": "60",


"expiration_date": "36개월",


"usage": "기초 손질 마지막 단계에서 자외선에 노출되기 쉬운 얼굴과 목 등에 골고루 발라줍니다.",


"origin": "한국",


"ingredients": "정제수, 사이클로메티콘, 징크옥사이드, 티타늄디옥사이드, 폴리글리세릴-3폴리다이메틸실록시에틸다이메티콘, 프로판다이올, 다이카프릴릴카보네이트, 카프릴릴메티콘, 세틸에틸헥사노에이트, 1,2-헥산다이올, 마그네슘설페이트, 다이스테아다이모늄헥토라이트, 하이드로젠다이메티콘, 알루미늄하이드록사이드, C30-45알킬세테아릴다이메티콘크로스폴리머, 폴리글리세릴-2다이폴리하이드록시스테아레이트, 스테아릭애씨드, 비사보롤, 이노시톨, 에틸헥실글리세린, 옥틸도데칸올, 글리세린, 소듐하이알루로네이트, 에키움 플란타기네움씨오일, 드럼스틱씨오일, 알부틴, 토코페릴아세테이트, 세라마이드엔피, 피토스핑고신, 풍선덩굴꽃/잎/덩굴추출물, 해바라기씨오일불검화물, 하이드로제네이티드레시틴, 다이부틸아디페이트, 솔비탄세스퀴올리에이트, 토코페롤, 향료",


"caution": "1. 화장품 사용 시 또는 사용 후 직사광선에 의하여 사용부위가 붉은 반점, 부어오름 또는 가려움증 등의 이상 증상이나 부작용이 있는 경우 전문의 등과 상담할 것 2. 상처가 있는 부위 등에는 사용을 자제할 것 3. 보관 및 취급 시의 주의사항 1) 어린이의 손이 닿지 않는 곳에 보관할 것 2) 직사광선을 피해서 보관할 것 4. 눈에 들어갔을 때에는 즉시 씻어낼 것"

},

{


"id": "e1617801-4368-46e0-824e-38f2a8257c86",


"name": "더 레이아웃 퍼펙트 프로텍션 선로션 60ml",


"price": "8010",


"brand": "RNW",


"image_url": "https://static.mynunc.com/ext/images/goods/top/22/01/14/06/BO00112821/0000256887.png",


"category": 5,


"site": 5,


"site_id": "BO00102394",


"link": "https://www.mynunc.com/product/goods/view-goods?goodsId=BO00102394&dspCateId=",


"site_category": "20000139",


"volume": "60",


"expiration_date": "36개월",


"usage": "본품 적당량을 취해 피부에 골고루 펴 바른다.",


"origin": "한국",


"ingredients": "정제수, 에칠헥실메톡시신나메이트, 부틸렌글라이콜, 에칠헥실살리실레이트, C12-15알킬벤조에이트, 디에칠아미노하이드록시벤조일헥실벤조에이트, 변성알코올, 호모살레이트, 옥토크릴렌, 티타늄디옥사이드, 사이클로펜타실록세인, 1,2-헥산다이올, 오렌지껍질오일, 팔마로사오일, 겨우살이잎추출물, 병풀추출물, 쇠비름추출물, 드럼스틱씨추출물, 다마스크장미꽃오일, 폴리아크릴레이트-13, 폴리메틸실세스퀴옥세인, 카프릴릭/카프릭/석시닉트라이글리세라이드, 폴리아이소부텐, 알루미늄스테아레이트, 글리세린, 폴리하이드록시스테아릭애씨드, 베헤닐알코올, 프로판다이올, 알루미나, 이눌린라우릴카바메이트, 폴리솔베이트20, 솔비탄아이소스테아레이트, 소듐스테아로일글루타메이트, 에틸헥실글리세린, 소듐하이알루로네이트, 아스코빌글루코사이드, 알란토인, 토코페롤, 소듐벤조에이트, 시트릭애씨드, 페녹시에탄올, 제라니올, 리날룰, 리모넨",


"caution": "1. 화장품 사용 시 또는 사용 후 직사광선에 의하여 사용부위가 붉은 반점, 부어오름 또는 가려움증 등의 이상 증상이나 부작용이 있는 경우 전문의 등과 상담할 것 2. 상처가 있는 부위 등에는 사용을 자제할 것 3. 보관 및 취급 시의 주의사항 1) 어린이의 손이 닿지 않는 곳에 보관할 것 2) 직사광선을 피해서 보관할 것 4. 눈에 들어갔을 때에는 즉시 씻어낼 것"

},

{


"id": "1bd0a88f-3dc7-45ef-a6f6-8d2c2a91bb0e",


"name": "아줄렌 마일드 UV 톤업 선 프라이머 50ml",


"price": "9250",


"brand": "써메딕",


"image_url": "https://static.mynunc.com/ext/images/goods/top/20/07/20/05/BO00101722/0000031971.jpg",


"category": 5,


"site": 5,


"site_id": "BO00101722",


"link": "https://www.mynunc.com/product/goods/view-goods?goodsId=BO00101722&dspCateId=",


"site_category": "20000139",


"volume": "50",


"expiration_date": "36개월",


"usage": "본품 적당량을 취해 자외선에 노출되는 부위에 골고루 펴 발라줍니다.",


"origin": "한국",


"ingredients": "정제수, C12-15알킬벤조에이트, 티타늄디옥사이드, 프로판다이올, 부틸옥틸살리실레이트, 나이아신아마이드, 카프릴릴메티콘, 카프릴릭/카프릭트라이글리세라이드, 폴리하이드록시스테아릭애씨드, 알루미늄스테아레이트, 1,2-헥산다이올, 펜틸렌글라이콜, 폴리메틸실세스퀴옥세인, 구아이아줄렌(1ppm), 알루미나, 암모늄아크릴로일다이메틸타우레이트/브이피코폴리머, 폴리아크릴레이트크로스폴리머-6, 세틸하이드록시에틸셀룰로오스, 셀룰로오스검, 하이드록시프로필메틸셀룰로오스, 소듐스테아로일글루타메이트, 부틸렌글라이콜, 스테아릭애씨드, 에틸헥실글리세린, 아데노신, t-부틸알코올, 글리세린, 판테놀, 알부틴, 하이드로제네이티드레시틴, 세테아릴알코올, 비피다발효용해물, 스페인감초뿌리추출물, 뽕나무껍질추출물, 병풀추출물, 빌베리열매/잎추출물, 황산앵초추출물, 세룰라타벚나무꽃추출물, 드럼스틱씨추출물, 라벤더꽃추출물, 포트마리골드꽃추출물, 카카두플럼추출물, 녹차추출물, 쇠비름추출물, 쌀추출물, 티트리잎추출물, 레몬추출물, 세라마이드엔피, 포타슘솔베이트, 하이드록시프로필사이클로덱스트린, 세라마이드엔에스, 피토스핑고신, 콜레스테롤, 하이알루로닉애씨드, 세라마이드에이에스, 세라마이드에이피, 글루타티온, 다이소듐이디티에이, 하이드롤라이즈드하이알루로닉애씨드, 소듐하이알루로네이트, 세라마이드이오피, 울트라마린, 향료",


"caution": "1. 화장품 사용 시 또는 사용 후 직사광선에 의하여 사용부위가 붉은 반점, 부어오름 또는 가려움증 등의 이상 증상이나 부작용이 있는 경우 전문의등과 상담할 것 2. 상처가 있는 부위 등에는 사용을 자제할 것 3. 보관 및 취급 시의 주의사항    가) 어린이의 손이 닿지 않는 곳에 보관할 것    나) 직사광선을 피해서 보관할 것 4. 눈에 들어갔을 때에는 즉시 씻어낼 것 5. 사용 후 물로 씻어내지 않으면 탈모 또는 탈색의 원인이 될 수 있으므로 주의할 것"

},

{


"id": "dfc3b337-6d0f-48ec-8f94-633ff6e3c239",


"name": "아줄렌 마일드 5.5 UV 프로텍트 선 50ml",


"price": "10250",


"brand": "써메딕",


"image_url": "https://static.mynunc.com/ext/images/goods/top/20/07/20/05/BO00101722/0000031971.jpg",


"category": 5,


"site": 5,


"site_id": "BO00101721",


"link": "https://www.mynunc.com/product/goods/view-goods?goodsId=BO00101721&dspCateId=",


"site_category": "20000139",


"volume": "50",


"expiration_date": "36개월",


"usage": "본품 적당량을 취해 자외선에 노출되는 부위에 골고루 펴 발라줍니다.",


"origin": "한국",


"ingredients": "\"정제수, 다이부틸아디페이트, 디에칠아미노하이드록시벤조일헥실벤조에이트, 에칠헥실트리아존, 메틸프로판다이올, 부틸옥틸살리실레이트, 다이카프릴릴카보네이트, 프로판다이올, 비스-에칠헥실옥시페놀메톡시페닐트리아진, 나이아신아마이드, C20-22알킬포스페이트, 세테아릴알코올, C20-22알코올, 부틸렌글라이콜, 1,2-헥산다이올, 펜틸렌글라이콜, 구아이아줄렌(500ppm), 베헤닐알코올, 글리세릴스테아레이트, 에탄올, 리아크릴레이트크로스폴리머-6, 트로메타민, 암모늄아크릴로일다이메틸타우레이트/브이피코폴리머, 소듐아크릴레이트/소듐아크릴로일다이메틸타우레이트코폴리머, 폴리아이소부텐, 에틸헥실글리세린, 아데노신, 카프릴릴/카프릴글루코사이드, 솔비탄올리에이트, t-부틸알코올, 토코페롤, 글리세린, 판테놀, 알부틴, 페퍼민트오일, 하이드로제네이티드레시틴, 스테아릭애씨드, 비피다발효용해물, 병풀추출물, 세룰라타벚나무꽃추출물, 드럼스틱씨추출물, 라벤더꽃추출물, 포트마리골드꽃추출물, 카카두플럼추출물, 녹차추출물, 쇠비름추출물, 브로콜리추출물, 세라마이드엔피, 포타슘솔베이트, 하이드록시프로필사이클로덱스트린, 세라마이드엔에스, 피토스핑고신, 콜레스테롤, 하이알루로닉애씨드, 세라마이드에이에스, 세라마이드에이피, 글루타티온, 다이소듐이디티에이, 하이드롤라이즈드하이알루로닉애씨드, 소듐하이알루로네이트, 세라마이드이오피, 향료",


"caution": "1. 화장품 사용 시 또는 사용 후 직사광선에 의하여 사용부위가 붉은 반점, 부어오름 또는 가려움증 등의 이상 증상이나 부작용이 있는 경우 전문의등과 상담할 것 2. 상처가 있는 부위 등에는 사용을 자제할 것 3. 보관 및 취급 시의 주의사항    가) 어린이의 손이 닿지 않는 곳에 보관할 것    나) 직사광선을 피해서 보관할 것 4. 눈에 들어갔을 때에는 즉시 씻어낼 것 5. 사용 후 물로 씻어내지 않으면 탈모 또는 탈색의 원인이 될 수 있으므로 주의할 것"

},

{


"id": "d9486498-a387-471f-a8c1-82e9ffd1899f",


"name": "니베아 선 영 에이지 페이스 크림 50ml (중건성, SPF50+)",


"price": "5372",


"brand": "니베아",


"image_url": "https://static.mynunc.com/ext/images/goods/top/20/07/20/05/BO00101722/0000031971.jpg",


"category": 5,


"site": 5,


"site_id": "BO00101413",


"link": "https://www.mynunc.com/product/goods/view-goods?goodsId=BO00101413&dspCateId=",


"site_category": "20000139",


"volume": "50",


"expiration_date": "제조일로부터 30개월",


"usage": "적당량을 눈가를 제외한 얼굴및 자외선 차단을 원하는 부위에 골고루 펴 발라 줍니다. 옷과의 직접적인 접촉은 피해주세요. ",


"origin": "독일 ",


"ingredients": "호모살레이트,부틸메톡시디벤조일메탄,에칠헥실살리실레이트,에칠헥실트리아존,비스-에칠헥실옥시페놀메톡시페닐트리아진,페닐벤즈이미다졸설포닉애씨드,정제수,글리세린,부틸렌글라이콜다이카프릴레이트/다이카프레이트,C12-15알킬벤조에이트,변성알코올,세테아릴알코올,다이스타치포스페이트,다이메티콘,글리세릴스테아레이트,페녹시에탄올,소듐하이드록사이드,소듐스테아로일글루타메이트,에칠헥실글리세린,향료,트라이소듐이디티에이,아크릴레이트/C10-30알킬아크릴레이트크로스폴리머, 카보머,토코페릴아세테이트,잔탄검,유비퀴논,감초추출물,소듐클로라이드 ",


"caution": "화장품을 사용하여 다음과 같은 이상이 있는 경우에는 사용을 중지하고 피부과전문의 등에세 상담할것 1.사용중붉은반점,부어오름,가려움증,자극등의 이상이 있는경우 2.적용부위가직사광선에 의하여위와같은이상이있는경우 3.상처가있는부위,습진및피부염등의 이상이 있는부위에는사용하지말것 4.보관및취급시 사용후에는 반드시 마개를 닫아두고 유아나 소아의손이닿지않는곳에 보관하며 고온또는저온의장소및직사광선이닿는곳에는보관하지말것 "

},

{


"id": "dc520187-5377-49ae-a39e-7f922efdc21d",


"name": "데일리 톤 업 선크림 SPF40 PA+++ 50ml",


"price": "8062",


"brand": "바세린",


"image_url": "https://static.mynunc.com/ext/images/goods/top/20/07/20/05/BO00101722/0000031971.jpg",


"category": 5,


"site": 5,


"site_id": "BO00100618",


"link": "https://www.mynunc.com/product/goods/view-goods?goodsId=BO00100618&dspCateId=",


"site_category": "20000139",


"volume": "50",


"expiration_date": "36개월",


"usage": "스킨케어 마지막 단계에서 적당량을 취해 자외선이 노출되는 부위에 골고루 펴 바릅니다.",


"origin": "한국",


"ingredients": "정제수, 호모살레이트, 부틸렌글라이콜, 에칠헥실살리실레이트, 다이부틸아디페이트, 프로판다이올, 티타늄디옥사이드, 카프릴릭/카프릭트글리세라이드, 부틸옥틸살리실레이트, 1,2-헥산다이올, 에칠헥실트리아존, 베헤닐알코올, 소듐폴리아크릴레이트, 에틸헥실스테아레이트, 폴리하이드록시스테아릭애씨드, 코코-카프릴레이트/카프레이트, 메틸메타크릴레이트크로스폴리머, 글리세릴스테아레이트, 알루미나, 피이지-100스테아레이트, 스테아릭애씨드, 폴리아크릴레이트크로스폴리머-6, 에틸헥실글리세린, 페트롤라툼(0.0.5%), 트라이데세스-6, 잔탄검, 트라이에톡시카프릴릴실레인, t-부틸알코올, 비에이치티, 토코페롤, 티타늄디옥사이드(CI77891), 향료, 리날룰, 리모넨, 부틸페닐메틸프로피오날, 헥실신나몰, 시트로넬올, 아밀신남알, 알파-아이소메틸아이오논, 제라니올, 쿠마린",


"caution": "1. 화장품 사용 시 또는 사용 후 직사광선에 의하여 사용부위가 붉은 반점, 부어오름 또는 가려움증 등의 이상 증상이나 부작용이 있는 경우 전문의 등과 상담할 것.2. 상처가 있는 부위 등에는 사용을 자제할 것 3. 보관 및 취급 주의사항 가)어린이의 손이 닿지 않는 곳에 보관할 것 나)직사광선을 피해서 보관할 것"

},

{


"id": "4f9f190b-2535-4d26-8283-91950b2fe4f9",


"name": "니베아 선 키즈 스윔 앤 플레이 선 로션 150ml (SPF50+)",


"price": "6732",


"brand": "니베아",


"image_url": "https://static.mynunc.com/ext/images/goods/top/20/07/20/05/BO00101722/0000031971.jpg",


"category": 5,


"site": 5,


"site_id": "BO00100597",


"link": "https://www.mynunc.com/product/goods/view-goods?goodsId=BO00100597&dspCateId=",


"site_category": "20000139",


"volume": "150",


"expiration_date": "제조일로부터 30개월",


"usage": "적당량을 눈가를 제외한 얼굴및 자외선 차단을 원하는 부위에 골고루 펴 발라 줍니다. 옷과의 직접적인 접촉은 피해주세요.",


"origin": "폴란드",


"ingredients": "정제수, 옥토크릴렌, 글리세린, 티타늄디옥사이드, 부틸메톡시디벤조일메탄, 부틸렌글라이콜디카프릴레이트/ 디카프레이트, C12-15알킬벤조에이트, 변성알코올, 비스-에칠헥실옥시페놀메톡시페닐트리아진, 디카프릴릴카보네이트 , 글리세릴스테아레이트시트레이트, 판테놀, 하이드로제네이티드코코-글리세라이드, 미리스틸미리스테이트, 토코페릴아세테이트, 스테아릴알코올, 브이피/헥사데센코폴리머, 잔탄검, 소듐아크릴레이트/C10-30알킬아크릴레이트크로스폴리머, 트리메톡시카프릴릴실란, 소듐시트레이트, 시트릭애씨드, 트리소듐이디티에이, 에칠헥실글리세린, 페녹시에탄올, 메칠파라벤, 에칠파라벤, 리날룰, 리모넨, 벤질알코올, 제라니올, 부틸페닐메칠프로피오날, 시트로넬올, 벤질살리실레이트, 신나밀알코올, 벤질벤조에이트, 시트랄, 향료",


"caution": "화장품을 사용하여 다음과 같은 이상이 있는 경우에는 사용을 중지하고 피부과 전문의 등에게 상담할 것 1.사용 중 붉은 반점, 부어오름, 가려움증, 자극 등의 이상이 있는 경우 2.적용 부위가 직사광선에 의하여 위와 같은 이상이 있는 경우 3.상처가 있는 부위, 습진 및 피부염 등의 이상이 있는 부위에는 사용하지 말 것 4. 보관 및 취급시 사용 후에는 반드시 마개를 닫아두고 유아나 소아의 손이 닿지 않는 곳에 보관하며 고온 또는 저온의 장소 및 직사광선이 닿는 곳에는 보관하지 말 것"

},

{


"id": "ad3ef7eb-d226-4bd7-b48a-dcff7935881b",


"name": "[그린핑거] 야외놀이 선크림 80ml",


"price": "8580",


"brand": "그린핑거",


"image_url": "https://static.mynunc.com/ext/images/goods/top/20/07/20/05/BO00101722/0000031971.jpg",


"category": 5,


"site": 5,


"site_id": "BO00100326",


"link": "https://www.mynunc.com/product/goods/view-goods?goodsId=BO00100326&dspCateId=",


"site_category": "20000139",


"volume": "80",


"expiration_date": "30개월",


"usage": "외출하기 30분전, 자외선에 노출되는 부분에 부드럽게 펴 발라 주세요",


"origin": "대한민국",


"ingredients": "정제수, 사이클로펜타실록세인, 에칠헥실메톡시신나메이트, 징크옥사이드, 에칠헥실살리실레이트, 티타늄디옥사이드, 다이프로필렌글라이콜, 피이지-10다이메티콘, 부틸렌글라이콜, 다이카프릴릴카보네이트, 다이스테아다이모늄헥토라이트, 토코페릴아세테이트, 바오밥나무씨오일, 알로에베라잎추출물, 드럼스틱씨오일, 포트마리골드꽃추출물, 병풀추출물, 마그네슘설페이트, 알루미늄하이드록사이드, 다이메티콘, 비스-에칠헥실옥시페놀메톡시페닐트리아진, 칼슘알루미늄보로실리케이트, 스테아릭애씨드, 다이메티콘/비닐다이메티콘크로스폴리머, 카프릴릴글라이콜, 에틸헥실글리세린, 메티콘, 폴리글리세릴-6폴리리시놀리에이트, 마이크로크리스탈린셀룰로오스, 셀룰로오스검, 소듐하이알루로네이트, 펜틸렌글라이콜, 1,2-헥산다이올, 토코페롤, 향료",


"caution": "1. 화장품을 사용하여 다음과 같은 이상이 있는 경우에는 사용을 중지하여야 하며, 계속 사용하면 증상이 약화되므로 피부과 전문의 등에게 상담하십시오. 1) 사용 중 붉은 반점, 부어오름, 가려움증, 자극 등의 이상이 있을 경우 2) 적용 부위가 직사광선에 의하여 위와 같은 이상이 있을 경우 2. 상처가 있는 부위, 습진 및 피부염 등의 이상이 있는 부위에는 사용하지 마십시오. 3. 보관 및 취급 시의 주의사항 1) 사용 후에는 반드시 마개를 닫아두십시오. 2) 유아,소아의 손이 닿지 않는 곳에 보관하십시오. 3) 고온 또는 저온의 장소 및 직사광선이 닿는 곳에는 보관하지 마십시오. 4. 눈에 들어갔을 때에는 즉시 씻어낼 것"

},

{


"id": "356eca5b-9877-41ee-9e16-ca47bec1c6e7",


"name": "모이스트 카밍 릴리프 선 50ml",


"price": "17110",


"brand": "비브",


"image_url": "https://static.mynunc.com/ext/images/goods/top/20/07/20/05/BO00101722/0000031971.jpg",


"category": 5,


"site": 5,


"site_id": "BO00100191",


"link": "https://www.mynunc.com/product/goods/view-goods?goodsId=BO00100191&dspCateId=",


"site_category": "20000139",


"volume": "50",


"expiration_date": "개봉 전 36개월 / 개봉 후 12개월",


"usage": "적당량을 덜어 피부결을 따라 부드럽게 펴 발라준 후 가볍게 두드려 흡수시켜 줍니다.",


"origin": "대한민국",


"ingredients": "정제수, 사이클로헥사실록세인, 징크옥사이드, C12-15알킬벤조에이트, 티타늄디옥사이드, 프로판다이올, 다이카프릴릴카보네이트, 세틸에틸헥사노에이트, 1,2-헥산다이올, 글리세린, 폴리프로필실세스퀴옥세인, 마그네슘설페이트, 솔비탄세스퀴올리에이트, 하이드로젠다이메티콘, 다이스테아다이모늄헥토라이트, 베타인, 알루미늄하이드록사이드, 판테놀, 폴리글리세릴-2다이폴리하이드록시스테아레이트, 스타이렌/아크릴레이트코폴리머, 스테아릭애씨드, 다이메티콘/비닐다이메티콘크로스폴리머, 폴리글리세릴-3폴리리시놀리에이트, 베르가모트오일, 이노시톨, 만주자작나무수액, 펜틸렌글라이콜, 에틸헥실글리세린, 옥틸도데칸올, 살비아오일, 쿠쿠이나무씨오일, 부틸렌글라이콜, 에키움, 플란타기네움씨오일, 병풀추출물, 약모밀추출물, 멕시칸치아씨추출물, 풍선덩굴꽃/잎/덩굴추출물, 해바라기씨오일불검화물, 폴리글리세릴-3폴리다이메틸실록시에틸다이메티콘, 토코페롤, 리모넨, 리날룰",


"caution": "1. 화장품 사용 시 또는 사용 후 직사광선에 의하여 사용부위가 붉은 반점, 부어오름 또는 가려움증 등의 이상 증상이나 부작용이 있는 경우 전문의 등과 상담할 것 2. 상처가 있는 부위 등에는 사용을 자제할 것  3. 보관 및 취급 시의 주의사항 가) 어린이의 손이 닿지 않는 곳에 보관할 것  나) 직사광선을 피해서 보관할 것"

},

{


"id": "8671361e-79d4-414e-a791-de732dd745e6",


"name": "모이스트 카밍 데일리 선 50ml",


"price": "14000",


"brand": "비브",


"image_url": "https://static.mynunc.com/ext/images/goods/top/20/07/20/05/BO00101722/0000031971.jpg",


"category": 5,


"site": 5,


"site_id": "BO00100190",


"link": "https://www.mynunc.com/product/goods/view-goods?goodsId=BO00100190&dspCateId=",


"site_category": "20000139",


"volume": "50",


"expiration_date": "개봉 전 36개월 / 개봉 후 12개월",


"usage": "적당량을 덜어 피부결을 따라 부드럽게 펴 발라준 후 가볍게 두드려 흡수시켜 줍니다.",


"origin": "대한민국",


"ingredients": "정제수, 다이부틸아디페이트, 에칠헥실트리아존, C12-15알킬벤조에이트, 부틸렌글라이콜, 프로판다이올, 다이카프릴릴카보네이트, 티타늄디옥사이드, 글리세린, 사이클로헥사실록세인, 디에칠아미노하이드록시벤조일헥실벤조에이트, 아라키딜알코올, 1,2-헥산다이올, 글리세레스-26, 베타인, 비스-에칠헥실옥시페놀메톡시페닐트리아진, 시어버터, 베헤닐알코올, 이노시톨, 암모늄아크릴로일다이메틸타우레이트/베헤네스-25메타크라일레이트크로스폴리머, 소듐아크릴레이트/소듐아크릴로일다이메틸타우레이트코폴리머, 알루미늄스테아레이트, 아라키딜글루코사이드, 메틸메타크릴레이트크로스폴리머, 폴리하이드록시스테아릭애씨드, 소듐스테아로일글루타메이트, 폴리아이소부텐, 하이드록시에틸우레아, 베르가모트오일, 알루미나, 트라넥사믹애씨드, 만주자작나무수액, 다이포타슘글리시리제이트, 에틸헥실글리세린, 잔탄검, 옥틸도데칸올, 솔비탄올리에이트, 카프릴릴/카프릴글루코사이드, 살비아오일, 쿠쿠이나무씨오일, 글루코오스, 에키움 플란타기네움씨오일, 풍선덩굴꽃/잎/덩굴추출물, 해바라기씨오일불검화물, 병풀추출물, 아크릴레이트/C10-30알킬아크릴레이트크로스폴리머, 약모밀추출물, 멕시칸치아씨추출물, 토코페롤, 시트릭애씨드, 리모넨, 리날룰",


"caution": "1. 화장품 사용 시 또는 사용 후 직사광선에 의하여 사용부위가 붉은 반점, 부어오름 또는 가려움증 등의 이상 증상이나 부작용이 있는 경우 전문의 등과 상담할 것 2. 상처가 있는 부위 등에는 사용을 자제할 것  3. 보관 및 취급 시의 주의사항 가) 어린이의 손이 닿지 않는 곳에 보관할 것  나) 직사광선을 피해서 보관할 것"

},

{


"id": "08e274a5-0eff-4f42-a3c6-d9fb6d010453",


"name": "[미샤] 시카딘 센텔라 그린 선 밀크 SPF50+/PA++++ 70ml",


"price": "23800",


"brand": "미샤",


"image_url": "https://static.mynunc.com/ext/images/goods/top/20/07/20/05/BO00101722/0000031971.jpg",


"category": 5,


"site": 5,


"site_id": "BO00100013",


"link": "https://www.mynunc.com/product/goods/view-goods?goodsId=BO00100013&dspCateId=",


"site_category": "20000139",


"volume": "70",


"expiration_date": "36개월",


"usage": "상세페이지 참조",


"origin": "한국",


"ingredients": "정제수, 징크옥사이드, 사이클로헥사실록세인, 프로필헵틸카프릴레이트, 다이실록세인, 프로판다이올, 티타늄디옥사이드, 아이소트라이데실아이소노나노에이트, 병풀추출물, 라벤더오일, 인도멀구슬나무잎추출물, 인도멀구슬나무꽃추출물, 아이비고드열매추출물, 가지열매추출물, 울금뿌리추출물, 홀리바질잎추출물, 드럼스틱씨오일, 참산호말추출물, 1,2-헥산다이올, 폴리메틸실세스퀴옥세인, 스테아릭애씨드, 알루미늄하이드록사이드, 아이소도데케인, 메틸메타크릴레이트크로스폴리머, 소듐클로라이드, 트라이에톡시카프릴릴실레인, 프로필렌글라이콜다이카프릴레이트/다이카프레이트, 비닐다이메티콘/메티콘실세스퀴옥세인크로스폴리머, 다이메티콘/비닐다이메티콘크로스폴리머, 다이스테아다이모늄헥토라이트, 에틸헥실글리세린, 잔탄검, 프로필렌카보네이트, 호박가루, 토코페롤, 칼라민, 마데카소사이드(1ppm), 클로렐라 불가리스가루, 리날룰, 리모넨",


"caution": "1) 화장품 사용 시 또는 사용 후 직사광선에 의하여 사용부위가 붉은 반점, 부어오름 또는 가려움증 등의 이상 증상이나 부작용이 있는 경우 전문의 등과 상담할 것 2) 상처가 있는 부위 등에는 사용을 자제할 것 3) 보관 및 취급 시의 주의사항 가) 어린이의 손이 닿지 않는 곳에 보관할 것 나) 직사광선을 피해서 보관할 것"

},

{


"id": "467988fb-2f87-420f-aa1c-e4569f5792ae",


"name": "어반쉐이드 모이스처 리페어 선 기획세트",


"price": "10200",


"brand": "듀이트리",


"image_url": "https://static.mynunc.com/ext/images/goods/top/20/07/20/05/BO00101722/0000031971.jpg",


"category": 5,


"site": 5,


"site_id": "BO00100158",


"link": "https://www.mynunc.com/product/goods/view-goods?goodsId=BO00100158&dspCateId=",


"site_category": "20000139",


"volume": "선크림 50ml / 클렌저 50",


"expiration_date": "30개월",


"usage": "상세페이지 참조",


"origin": "대한민국",


"ingredients": "정제수, 다이부틸아디페이트, 다이카프릴릴카보네이트, 프로판다이올, 글리세린, 부틸옥틸살리실레이트, 티타늄디옥사이드, 디에칠아미노하이드록시벤조일헥실벤조에이트, 폴리실리콘-15, 나이아신아마이드, 에칠헥실트리아존, 1,2-헥산다이올, 세테아릴올리베이트, 세테아릴알코올, 펜틸렌글라이콜, 솔비탄올리베이트, 하이드록시프로필트라이모늄하이알루로네이트, 소듐하이알루로네이트, 소듐아세틸레이티드하이알루로네이트, 하이드롤라이즈드하이알루로닉애씨드, 하이알루로닉애씨드, 소듐하이알루로네이트크로스폴리머, 하이드롤라이즈드소듐하이알루로네이트, 판테놀, 보검선인장줄기추출물, 미역추출물, 스피룰리나 플라텐시스추출물, 감태추출물, 오렌지껍질오일, 인도멀구슬나무잎추출물, 호호바씨오일, 필리핀오렌지껍질오일, 인도멀구슬나무꽃추출물, 몰로키아잎추출물, 리씨열매오일, 보리추출물, 알바수련꽃추출물, 베헤닐알코올, C14-22알코올, 폴리글리세릴-2카프레이트, 펜타에리스리틸테트라-다이-t-부틸하이드록시하이드로신나메이트, 수크로오스스테아레이트, 암모늄아크릴로일다이메틸타우레이트/브이피코폴리머, 스테아릭애씨드, C12-20알킬글루코사이드, 알루미나, 이눌린라우릴카바메이트, 글리세릴카프릴레이트, 에틸헥실글리세린, 잔탄검, 아데노신, 스쿠알란, 토코페롤, 부틸렌글라이콜, 다이프로필렌글라이콜, 소듐팔미토일프롤린, 리모넨, 시트랄, 리날룰",


"caution": "1. 화장품 사용 시 또는 사용 후 직사광선에 의하여 사용부위가 붉은 반점, 부어오름 또는 가려움증 등의 이상 증상이나 부작용이 있는 경우 전문의 등과 상담할 것 2. 상처가 있는 부위 등에는 사용을 자제할 것 3. 보관 및 취급 시의 주의사항 가) 어린이의 손이 닿지 않는 곳에 보관할 것 나) 직사광선을 피해서 보관할 것 * 사용 전에 반드시 사용법 및 사용 시의 주의사항을 숙지하신 후 사용하십시오."

},

{


"id": "8d9ca5ee-dc05-40f3-8f60-721f9c21a075",


"name": "슈퍼에어핏 마일드 선크림 노세범",


"price": "16000",


"brand": "어퓨",


"image_url": "https://static.mynunc.com/ext/images/goods/top/20/07/20/05/BO00101722/0000031971.jpg",


"category": 5,


"site": 5,


"site_id": "BO00100045",


"link": "https://www.mynunc.com/product/goods/view-goods?goodsId=BO00100045&dspCateId=",


"site_category": "20000139",


"volume": "50",


"expiration_date": "발송일로부터 사용기한이 18개월 이상 남은 제품으로 발송",


"usage": "상세페이지참조",


"origin": "한국",


"ingredients": "정제수, 사이클로메티콘, 징크옥사이드 (CI 77947), 폴리글리세릴-3폴리다이메틸실록시에틸다이메티콘, 티타늄디옥사이드 (CI 77891), 부틸옥틸살리실레이트, 다이페닐실록시페닐트라이메티콘, 글리세린, 에탄올, 아이소도데케인, 부틸렌글라이콜, 다이부틸아디페이트, 하이드로제네이티드폴리아이소부텐, 폴리메틸메타크릴레이트, 다이스테아다이모늄헥토라이트, 폴리글리세릴-2다이폴리하이드록시스테아레이트, 폴리메틸실세스퀴옥세인, 실리카, 비닐다이메티콘/메티콘실세스퀴옥세인크로스폴리머, 마그네슘설페이트, 다이메티콘/비닐다이메티콘크로스폴리머, 트라이에톡시카프릴릴실레인, 1,2-헥산다이올, 알루미늄하이드록사이드, 스테아릭애씨드, 카프릴릴글라이콜, 하이드록시아세토페논, 아크릴레이트코폴리머, 아크릴레이트/폴리트라이메틸실록시메타크릴레이트코폴리머, 아시아티코사이드, 아시아틱애씨드, 마데카식애씨드, 향료",


"caution": "1. 화장품 사용 시 또는 사용 후 직사광선에 의하여 사용부위가 붉은 반점, 부어오름 또는 가려움증 등의 이상 증상이나 부작용이 있는 경우 전문의 등과 상담할 것 2. 상처가 있는 부위 등에는 사용을 자제할 것 3. 보관 및 취급 시의 주의사항 가. 어린이의 손이 닿지 않는 곳에 보관할 것 나. 직사광선을 피해서 보관할 것"

},

{


"id": "4645bcde-4dac-41fe-bd84-dc83f273826e",


"name": "슈퍼에어핏 마일드 선크림 워터풀",


"price": "16000",


"brand": "어퓨",


"image_url": "https://static.mynunc.com/ext/images/goods/top/20/07/20/05/BO00101722/0000031971.jpg",


"category": 5,


"site": 5,


"site_id": "BO00100042",


"link": "https://www.mynunc.com/product/goods/view-goods?goodsId=BO00100042&dspCateId=",


"site_category": "20000139",


"volume": "50",


"expiration_date": "발송일로부터 사용기한이 18개월 이상 남은 제품으로 발송",


"usage": "상세페이지참조",


"origin": "한국",


"ingredients": "정제수, 다이부틸아디페이트, 부틸옥틸살리실레이트, 다이프로필렌글라이콜, 폴리실리콘-15, 디에칠아미노하이드록시벤조일헥실벤조에이트, 실리카, 에칠헥실트리아존, C12-15알킬벤조에이트, 이소아밀p-메톡시신나메이트, 세테아릴올리베이트, 솔비탄올리베이트, 세테아릴알코올, 사이클로헥사실록세인, 카프릴릴글라이콜, 글리세릴스테아레이트, 포타슘세틸포스페이트, 솔비탄스테아레이트, 향료, 에틸헥실글리세린, 코코-글루코사이드, 1,2-헥산다이올, 트로메타민, 아크릴레이트/C10-30알킬아크릴레이트크로스폴리머, 다이소듐이디티에이, 글루코오스, 아시아티코사이드, 아시아틱애씨드, 마데카식애씨드",


"caution": "1. 화장품 사용 시 또는 사용 후 직사광선에 의하여 사용부위가 붉은 반점, 부어오름 또는 가려움증 등의 이상 증상이나 부작용이 있는 경우 전문의 등과 상담할 것 2. 상처가 있는 부위 등에는 사용을 자제할 것 3. 보관 및 취급 시의 주의사항 가. 어린이의 손이 닿지 않는 곳에 보관할 것 나. 직사광선을 피해서 보관할 것"

},

{


"id": "99105cce-cc27-44d6-93f0-4deae58a9669",


"name": "슈퍼에어핏 마일드 선베이스 01 핑크",


"price": "20000",


"brand": "어퓨",


"image_url": "https://static.mynunc.com/ext/images/goods/top/20/07/20/05/BO00101722/0000031971.jpg",


"category": 5,


"site": 5,


"site_id": "BO00100016",


"link": "https://www.mynunc.com/product/goods/view-goods?goodsId=BO00100016&dspCateId=",


"site_category": "20000139",


"volume": "50",


"expiration_date": "발송일로부터 사용기한이 18개월 이상 남은 제품으로 발송",


"usage": "적당량을 덜어낸 후 얼굴에 도포하여 펴 발라줍니다.",


"origin": "한국",


"ingredients": "정제수, 에칠헥실메톡시신나메이트, 부틸렌글라이콜, 에칠헥실살리실레이트, 글리세린, 티타늄디옥사이드 (CI 77891), 사이클로펜타실록세인, 디에칠아미노하이드록시벤조일헥실벤조에이트, 사이클로헥사실록세인, 나이아신아마이드, 옥토크릴렌, 옥틸도데칸올, 펜틸렌글라이콜, 다이카프릴릴카보네이트, 다이페닐실록시페닐트라이메티콘, 트라이세테아레스-4포스페이트, 글라이콜스테아레이트, 글리세릴스테아레이트, 피이지-100스테아레이트, 피이지-2스테아레이트, 포타슘세틸포스페이트, 알루미늄하이드록사이드, 스테아릭애씨드, 암모늄아크릴로일다이메틸타우레이트/브이피코폴리머, 하이드록시에틸아크릴레이트/소듐아크릴로일다이메틸타우레이트코폴리머, 라우릴피이지-9폴리다이메틸실록시에틸다이메티콘, 스쿠알란, 트로메타민, 카프릴릴글라이콜, 에틸헥실글리세린, 폴리솔베이트60, 아데노신, 솔비탄아이소스테아레이트, 트라이에톡시카프릴릴실레인, 토코페롤, 아시아티코사이드, 아시아틱애씨드, 마데카식애씨드, 카보머, 다이소듐이디티에이, 페녹시에탄올, 향료, 울트라마린 (CI 77007), 마이카 (CI 77019), 적색산화철 (CI 77491)",


"caution": "1. 화장품 사용 시 또는 사용 후 직사광선에 의하여 사용부위가 붉은 반점, 부어오름 또는 가려움증 등의 이상 증상이나 부작용이 있는 경우 전문의 등과 상담할 것 2. 상처가 있는 부위 등에는 사용을 자제할 것 3. 보관 및 취급 시의 주의사항 가. 어린이의 손이 닿지 않는 곳에 보관할 것 나. 직사광선을 피해서 보관할 것"

},

{


"id": "5a70c5e4-3476-4d4d-83cb-94ef81bbb6e7",


"name": "슈퍼에어핏 마일드 선크림 데일리",


"price": "16000",


"brand": "어퓨",


"image_url": "https://static.mynunc.com/ext/images/goods/top/20/07/20/05/BO00101722/0000031971.jpg",


"category": 5,


"site": 5,


"site_id": "BO00100015",


"link": "https://www.mynunc.com/product/goods/view-goods?goodsId=BO00100015&dspCateId=",


"site_category": "20000139",


"volume": "50",


"expiration_date": "발송일로부터 사용기한이 18개월 이상 남은 제품으로 발송",


"usage": "상품 상세 설명 참조",


"origin": "한국",


"ingredients": "정제수, C12-15알킬벤조에이트, 티타늄디옥사이드, 프로판다이올, 메틸트라이메티콘, 부틸렌글라이콜, 사이클로헥사실록세인, 실리카, 폴리메틸실세스퀴옥세인, 알루미늄스테아레이트, 폴리하이드록시스테아릭애씨드, 1,2-헥산다이올, 펜틸렌글라이콜, 카프릴릭/카프릭트라이글리세라이드, 알루미나, 암모늄아크릴로일다이메틸타우레이트/브이피코폴리머, 폴리아크릴레이트크로스폴리머-6, 소듐아크릴레이트/소듐아크릴로일다이메틸타우레이트코폴리머, 소듐스테아로일글루타메이트, 폴리아이소부텐, 하이드록시프로필메틸셀룰로오스스테아록시에터, 스테아릭애씨드, 에틸헥실글리세린, 잔탄검, 솔비탄올리에이트, 카프릴릴/카프릴글루코사이드, t-부틸알코올, 토코페롤, 마데카식애씨드, 아시아티코사이드, 아시아틱애씨드, 향료",


"caution": "1. 화장품 사용 시 또는 사용 후 직사광선에 의하여 사용부위가 붉은 반점, 부어오름 또는 가려움증 등의 이상 증상이나 부작용이 있는 경우 전문의 등과 상담할 것 2. 상처가 있는 부위 등에는 사용을 자제할 것 3. 보관 및 취급 시의 주의사항 가. 어린이의 손이 닿지 않는 곳에 보관할 것 나. 직사광선을 피해서 보관할 것"

},

{


"id": "34c4e4a2-bc7d-43fa-aa83-f4c1fcf30e96",


"name": "[미샤] 초공진 설본 미백 선크림 50ml",


"price": "19800",


"brand": "미샤",


"image_url": "https://static.mynunc.com/ext/images/goods/top/20/07/20/05/BO00101722/0000031971.jpg",


"category": 5,


"site": 5,


"site_id": "BO00084809",


"link": "https://www.mynunc.com/product/goods/view-goods?goodsId=BO00084809&dspCateId=",


"site_category": "20000139",


"volume": "50",


"expiration_date": "36개월",


"usage": "상품 상세 설명 참조",


"origin": "한국",


"ingredients": "정제수, 호모살레이트, 에칠헥실살리 실레이트, 티타늄디옥사이드, 부틸렌글라이콜, 디에칠아미노하이드록시벤조일헥실벤조에이 트, 다이프로필렌글라이콜, 카프릴릴메티콘, 부틸옥틸살리실레이트, 카프릴릭/카프릭트라 이글리세라이드, 변성알코올, 메틸메타크릴레이 트크로스폴리머, 나이아신아마이드, C20-22 알킬포스페이트, 아라키딜알코올, 비스-에칠 헥실옥시페놀메톡시페닐트리아진, C20-22알 코올, 베헤닐알코올, 다이메티콘, 다이카프릴릴 에터, 다이카프릴릴카보네이트, 알루미늄하이드 록사이드, 스테아릭애씨드, 당느릅나무뿌리추출 물, 제비꽃꽃추출물, 다시마추출물, 알로에베라 잎추출물, 참마뿌리추출물, 아라키딜글루코사이드, 카프릴릴글라이콜, 포타슘세틸포스페이트, 하이 드록시에틸아크릴레이트/소듐아크릴로일다이 메틸타우레이트코폴리머, 글리세린, 에틸헥실 글리세린, 솔비탄스테아레이트, 토코페릴아세 테이트, 인삼추출물, 복령균핵추출물, 소나무잎 추출물, 작약추출물, 쌀추출물, 둥근잎나팔꽃추출 물, 오미자추출물, 녹용추출물, 은행추출물, 국화 추출물, 산수유열매추출물, 잇꽃꽃추출물, 자작 나무껍질추출물, 아스퍼질러스발효물, 가회톱 뿌리추출물, 참당귀뿌리추출물, 스쿠알란, 마이 크로크리스탈린셀룰로오스, 글리세릴스테아 레이트, 피이지-100스테아레이트, 폴리아크릴 레이트크로스폴리머-6, 1,2-헥산다이올, 다이 소듐이디티에이, 아데노신, 폴리솔베이트60, 셀룰로오스검, 솔비탄아이소스테아레이트, 글루 코오스, t-부틸알코올, 토코페롤, 향료, 트라넥사믹애씨드, 벤질벤조에이트, 리모넨",


"caution": "1) 화장품 사용 시 또는 사용 후 직사광선에 의하여 사용부위가 붉은 반점, 부어오름 또는 가려움증 등의 이상 증상이나 부작용이 있는 경우 전문의 등과 상담할 것 2) 상처가 있는 부위 등에는 사용을 자제할 것 3) 보관 및 취급 시의 주의사항 가) 어린이의 손이 닿지 않는 곳에 보관할 것 나) 직사광선을 피해서 보관할 것"

},

{


"id": "4eaf08d1-5240-43bc-967e-91df6b37d56f",


"name": "[미샤] 올 어라운드 세이프 블록 워터프루프 패밀리 선 로션 SPF50+ PA+++ 200g",


"price": "29800",


"brand": "미샤",


"image_url": "https://static.mynunc.com/ext/images/goods/top/20/07/20/05/BO00101722/0000031971.jpg",


"category": 5,


"site": 5,


"site_id": "BO00100014",


"link": "https://www.mynunc.com/product/goods/view-goods?goodsId=BO00100014&dspCateId=",


"site_category": "20000139",


"volume": "200g",


"expiration_date": "12개월",


"usage": "상세페이지 참조",


"origin": "한국",


"ingredients": "정제수,사이클로펜타실록세인,에칠헥실메톡시신나메이트,에칠헥실살리실레이트,글리세린,징크옥사이드 (CI 77947),피이지-10다이메티콘,티타늄디옥사이드 (CI 77891),다이메티콘,다이프로필렌글라이콜,쇠비름추출물,마그네슘설페이트,다이스테아다이모늄헥토라이트,C30-45알킬세테아릴다이메티콘크로스폴리머,이소아밀p-메톡시신나메이트,비닐다이메티콘/메티콘실세스퀴옥세인크로스폴리머,알루미늄하이드록사이드,스테아릭애씨드,부틸렌글라이콜,카페인,다이소듐이디티에이,페녹시에탄올,포타슘솔베이트,향료",


"caution": "1) 화장품 사용 시 또는 사용 후 직사광선에 의하여 사용부위가 붉은 반점, 부어오름 또는 가려움증 등의 이상 증상이나 부작용이 있는 경우 전문의 등과 상담할 것 2) 상처가 있는 부위 등에는 사용을 자제할 것 3) 보관 및 취급 시의 주의사항 가) 어린이의 손이 닿지 않는 곳에 보관할 것 나) 직사광선을 피해서 보관할 것"

},

{


"id": "21928fc4-65b5-4808-b31e-ade64c81d531",


"name": "[네시픽] 프레쉬 허브 오리진 선 블록 50ml",


"price": "8400",


"brand": "네시픽",


"image_url": "https://static.mynunc.com/ext/images/goods/top/20/07/20/05/BO00101722/0000031971.jpg",


"category": 5,


"site": 5,


"site_id": "BO00084722",


"link": "https://www.mynunc.com/product/goods/view-goods?goodsId=BO00084722&dspCateId=",


"site_category": "20000139",


"volume": "50",


"expiration_date": "36개월",


"usage": "상품 상세 설명 참조",


"origin": "대한민국",


"ingredients": "정제수, 호모살레이트, 부틸렌글라이콜, 디프로필렌글라이콜, 에칠헥실살리실레이트,메칠메타크릴레이트크로스폴리머, 부틸메톡시디벤조일메탄, 페닐벤즈이미다졸설포닉애씨드, C12-15알킬벤조에이트, 세테아릴알코올, 글리세릴스테아레이트, 세테아릴올리베이트, 옥토크릴렌, 카렌둘라꽃수(9,200ppm), 카렌둘라추출물(5ppm), 밤껍질추출물, 라벤더꽃추출물(35ppm), 녹차추출물, 덩굴월귤열매추출물, 베르가모트열매오일(1,400ppm), 센티드제라늄꽃오일(360ppm), 라반딘오일(150ppm), 일랑일랑꽃오일(90ppm), 소르비탄올리베이트, 폴리소르베이트60, 디메치콘, 폴리아크릴레이트-13, 소듐하이드록사이드, 피이지-100스테아레이트, 소르비탄스테아레이트, 폴리이소부텐, 비에이치티, 폴리소르베이트20, 소르비탄이소스테아레이트, 디소듐이디티에이, 카프릴릴글라이콜, 에칠헥실글리세린, 1,2-헥산디올",


"caution": "1. 화장품 사용 시 또는 사용 후 직사광선에 의하여 사용부위가 붉은 반점, 부어오름 또는 가려움증 등의 이상 증상이나 부작용이 있는 경우 전문의 등과 상담할 것 2. 상처가 있는 부위 등에는 사용을 자제할 것 3. 보관 및 취급 시의 주의사항 가) 어린이의 손이 닿지 않는 곳에 보관할 것 나) 직사광선을 피해서 보관할 것"

},

{


"id": "f73b84ec-6dc0-442c-a7e2-f0acc4f4dce7",


"name": "세이프 블록RX 히알론 수딩 선 50ml",


"price": "21800",


"brand": "미샤",


"image_url": "https://static.mynunc.com/ext/images/goods/top/20/07/20/05/BO00101722/0000031971.jpg",


"category": 5,


"site": 5,


"site_id": "BO00084464",


"link": "https://www.mynunc.com/product/goods/view-goods?goodsId=BO00084464&dspCateId=",


"site_category": "20000139",


"volume": "50",


"expiration_date": "36개월",


"usage": "상품 상세 설명 참조",


"origin": "한국",


"ingredients": "정제수,다이부틸아디페이트,에탄올,부틸옥틸살리실레이트,디에칠아미노하이드록시벤조일헥실벤조에이트,비스-에칠헥실옥시페놀메톡시페닐트리아진,부틸렌글라이콜,에칠헥실트리아존,메틸메타크릴레이트크로스폴리머,나이아신아마이드,한련초추출물,인도멀구슬나무잎추출물,카카오씨추출물,드럼스틱씨오일,소듐하이알루로네이트,하이드롤라이즈드하이알루로닉애씨드,하이알루로닉애씨드,라즈베리케톤,이소아밀p-메톡시신나메이트,펜틸렌글라이콜,폴리메틸실세스퀴옥세인,폴리실리콘-15,소듐아크릴레이트/소듐아크릴로일다이메틸타우레이트코폴리머,폴리아이소부텐,글리세릴카프릴레이트,카프릴릴글라이콜,아크릴레이트코폴리머,에틸헥실글리세린,아데노신,카프릴릴/카프릴글루코사이드,솔비탄올리에이트,덱스트린,프로판다이올,소듐하이알루로네이트크로스폴리머,하이드롤라이즈드글라이코사미노글리칸,글리세린,벤질글라이콜,토코페롤,다이소듐이디티에이,세테아릴알코올,향료",


"caution": "1) 화장품 사용 시 또는 사용 후 직사광선에 의하여 사용부위가 붉은 반점, 부어오름 또는 가려움증 등의 이상 증상이나 부작용이 있는 경우 전문의 등과 상담할 것 2) 상처가 있는 부위 등에는 사용을 자제할 것 3) 보관 및 취급 시의 주의사항 가) 어린이의 손이 닿지 않는 곳에 보관할 것 나) 직사광선을 피해서 보관할 것"

},

{


"id": "8f226e46-1b30-4959-b313-594470048699",


"name": "세이프 블록RX 커버 톤업 선 50ml",


"price": "21800",


"brand": "미샤",


"image_url": "https://static.mynunc.com/ext/images/goods/top/20/07/20/05/BO00101722/0000031971.jpg",


"category": 5,


"site": 5,


"site_id": "BO00084463",


"link": "https://www.mynunc.com/product/goods/view-goods?goodsId=BO00084463&dspCateId=",


"site_category": "20000139",


"volume": "50",


"expiration_date": "36개월",


"usage": "상품 상세 설명 참조",


"origin": "한국",


"ingredients": "정제수, 티타늄디옥사이드, 카프릴릭/카프릭트라이글리세라이드, 프로판다이올, 사이클로헥사실록세인, 나이아신아마이드, 아크릴레이트코폴리머, 폴리하이드록시스테아릭애씨드, 1,2-헥산다이올, 폴리메틸실세스퀴옥세인, 펜틸렌글라이콜, 다이메티콘/비닐다이메티콘크로스폴리머, 다이카프릴릴카보네이트, 실리카, 알루미나, 코코-카프릴레이트/카프레이트, 스테아릭애씨드, 다이메티콘올, 트라이실록세인, 소듐아크릴레이트/소듐아크릴로일다이메틸타우레이트코폴리머, 폴리아크릴레이트크로스폴리머-6, 폴리아이소부텐, 소듐폴리아크릴로일다이메틸타우레이트, 암모늄아크릴로일다이메틸타우레이트/브이피코폴리머, 에틸헥실글리세린, 하이드록시프로필메틸셀룰로오스스테아록시에터, 트라이에톡시카프릴릴실레인, 아데노신, 알루미늄하이드록사이드, 부틸렌글라이콜, 솔비탄올리에이트, 카프릴릴/카프릴글루코사이드, t-부틸알코올, 세라마이드엔피, 토코페롤, 향료, 황색산화철, 적색산화철, 흑색산화철",


"caution": "1) 화장품 사용 시 또는 사용 후 직사광선에 의하여 사용부위가 붉은 반점, 부어오름 또는 가려움증 등의 이상 증상이나 부작용이 있는 경우 전문의 등과 상담할 것 2) 상처가 있는 부위 등에는 사용을 자제할 것 3) 보관 및 취급 시의 주의사항 가) 어린이의 손이 닿지 않는 곳에 보관할 것 나) 직사광선을 피해서 보관할 것"

},

{


"id": "f49c9b5a-629a-4117-88bb-5c131af63925",


"name": "세이프 블록RX 징크 톤업 선 50ml",


"price": "21800",


"brand": "미샤",


"image_url": "https://static.mynunc.com/ext/images/goods/top/20/07/20/05/BO00101722/0000031971.jpg",


"category": 5,


"site": 5,


"site_id": "BO00084462",


"link": "https://www.mynunc.com/product/goods/view-goods?goodsId=BO00084462&dspCateId=",


"site_category": "20000139",


"volume": "50",


"expiration_date": "36개월",


"usage": "상품 상세 설명 참조",


"origin": "한국",


"ingredients": "정제수,징크옥사이드 (CI 77947),코코-카프릴레이트/카프레이트,부틸렌글라이콜,글리세린,메틸메타크릴레이트크로스폴리머,나이아신아마이드,펜틸렌글라이콜,폴리하이드록시스테아릭애씨드,칼라민,베헤네스-25,폴리메틸실세스퀴옥세인,트라이에톡시카프릴릴실레인,세테아릴올리베이트,솔비탄올리베이트,하이드록시에틸아크릴레이트/소듐아크릴로일다이메틸타우레이트코폴리머,글리세릴스테아레이트,암모늄아크릴로일다이메틸타우레이트/브이피코폴리머,카프릴릴글라이콜,카프릴릭/카프릭트라이글리세라이드,폴리아크릴레이트크로스폴리머-6,아데노신,스테아릭애씨드,세라마이드엔피,다이소듐이디티에이,잔탄검,향료,적색산화철 (CI 77491)",


"caution": "1) 화장품 사용 시 또는 사용 후 직사광선에 의하여 사용부위가 붉은 반점, 부어오름 또는 가려움증 등의 이상 증상이나 부작용이 있는 경우 전문의 등과 상담할 것 2) 상처가 있는 부위 등에는 사용을 자제할 것 3) 보관 및 취급 시의 주의사항 가) 어린이의 손이 닿지 않는 곳에 보관할 것 나) 직사광선을 피해서 보관할 것"

},

{


"id": "1ffedbad-70d0-4d7a-9eeb-c8f40ccd6120",


"name": "세이프 블록RX 올 파워풀 선 50ml",


"price": "21800",


"brand": "미샤",


"image_url": "https://static.mynunc.com/ext/images/goods/top/20/04/03/01/BO00084461/0000004931.jpg",


"category": 5,


"site": 5,


"site_id": "BO00084461",


"link": "https://www.mynunc.com/product/goods/view-goods?goodsId=BO00084461&dspCateId=",


"site_category": "20000139",


"volume": "50",


"expiration_date": "12개월",


"usage": "상품 상세 설명 참조",


"origin": "한국",


"ingredients": "정제수,사이클로메티콘,징크옥사이드 (CI 77947),다이카프릴릴카보네이트,티타늄디옥사이드 (CI 77891),다이프로필렌글라이콜,폴리글리세릴-3폴리다이메틸실록시에틸다이메티콘,세틸에틸헥사노에이트,프로판다이올,나이아신아마이드,페닐트라이메티콘,다이스테아다이모늄헥토라이트,카프릴릴메티콘,펜틸렌글라이콜,마그네슘설페이트,폴리메틸실세스퀴옥세인,1,2-헥산다이올,트라이에톡시카프릴릴실레인,알루미늄하이드록사이드,폴리하이드록시스테아릭애씨드,폴리글리세릴-2다이폴리하이드록시스테아레이트,스테아릭애씨드,C12-15알킬벤조에이트,아데노신,토코페롤,아이소스테아릭애씨드,세라마이드엔피,향료",


"caution": "1) 화장품 사용 시 또는 사용 후 직사광선에 의하여 사용부위가 붉은 반점, 부어오름 또는 가려움증 등의 이상 증상이나 부작용이 있는 경우 전문의 등과 상담할 것 2) 상처가 있는 부위 등에는 사용을 자제할 것 3) 보관 및 취급 시의 주의사항 가) 어린이의 손이 닿지 않는 곳에 보관할 것 나) 직사광선을 피해서 보관할 것"

},

{


"id": "1c1ea1a5-32ca-49e5-8392-0ffa98ac09e4",


"name": "화이트 인 밀크 썬 SPF50+ PA++++ 40g",


"price": "5900",


"brand": "지나인스킨",


"image_url": "https://static.mynunc.com/ext/images/goods/top/20/04/03/01/BO00084461/0000004931.jpg",


"category": 5,


"site": 5,


"site_id": "BO00083639",


"link": "https://www.mynunc.com/product/goods/view-goods?goodsId=BO00083639&dspCateId=",


"site_category": "20000139",


"volume": "40g",


"expiration_date": "제조일로부터 3년 이내",


"usage": "상품 상세 설명 참조",


"origin": "대한민국",


"ingredients": "정제수, 사이클로펜타실록산, 이소노닐이소노나노에이트, 부틸렌글라이콜, 사이클로헥사실록산, 에칠헥실메톡시신나메이트, 징크옥사이드, 피이지-10디메치콘, 디프로필렌글라이콜, 나이아신아마이드, 에탄올, 디메치콘, 디메치콘/피이지-10/15크로스폴리머, 디에칠아미노하이드록시벤조일헥실벤조에이트, 소르비탄세스퀴올리에이트, 실리카, 디스테아디모늄헥토라이트, C30-45알킬디메칠실릴폴리프로필실세스퀴옥산, 에칠헥산디올, 세레신, 비즈왁스, 향료, 디스테아릴디모늄클로라이드, 글리세릴카프릴레이트, 우유단백질추출물, 디소듐이디티에이, 아데노신, 감초추출물, 닥나무뿌리추출물, 달맞이꽃오일, 레몬수, 마시멜로뿌리추출물, 망고추출물, 알부틴, 에델바이스추출물, 쟈스민추출물, 접시꽃추출물, 판테놀, 해바라기씨오일, 토코페릴아세테이트, 산자나무열매추출물, 아마인추출물, 연꽃수, 오레가노잎추출물, 유칼립투스잎추출물, 히비스커스꽃추출물, 녹차추출물, 치아씨추출물, 서양송악잎추출물, 구주소나무잎추출물, 글리세린, 1,2-헥산디올, 백합추출물, 하이드록시프로필사이클로덱스트린, 아스코빅애씨드, 글루타치온",


"caution": "1. 화장품을 사용하여 다음과 같이 이상이 있을 경우에는 사용을 중지할 것이며, 계속 사용하면 증상을 악화시키므로 피부과 전문의 등에게 상담을 하십시오.1) 사용 중 붉은 반점, 부어오름, 가려움증, 자극 등의 이상이 있을 경우2) 적용부위가 직사광선에 의해 위와 같은 이상이 있을 경우 2. 상처가 있는 곳 또는 습진 및 피부염 등의 이상이 있는 부위에는 사용을 금합니다.3. 보관 및 취급상의 주의사항1) 사용 후에는 반드시 마개를 닫아두십시오.2) 유,소아의 손이 닿지 않는 곳에 보관하십시오.3) 고온 내지 저온의 장소 및 일광이 닿는 곳에는 보관하지 마십시오."

},

{


"id": "aa309c43-513f-4d4f-8a86-2926a26a1975",


"name": "[미샤] 맨즈큐어 선 에센스 수티드 포맨 50ml",


"price": "11800",


"brand": "미샤",


"image_url": "https://static.mynunc.com/ext/images/goods/top/20/04/03/01/BO00084461/0000004931.jpg",


"category": 5,


"site": 5,


"site_id": "BO00079639",


"link": "https://www.mynunc.com/product/goods/view-goods?goodsId=BO00079639&dspCateId=",


"site_category": "20000139",


"volume": "50",


"expiration_date": "36개월",


"usage": "상품 상세 설명 참조",


"origin": "한국",


"ingredients": "정제수, 호모살레이트, 변성알코올, 에칠헥실살리실레이트, 메틸메타크릴레이트크로스폴리머, 부틸메톡시디벤조일메탄, 비스-에칠헥실옥시페놀메톡시페닐트리아진, 다이프로필렌글라이콜, 이소아밀p-메톡시신나메이트, 옥토크릴렌, 부틸아보카데이트, 프로필갈레이트, 돌콩싹추출물, 목련나무껍질추출물, 에필로비움 플레이스케리추출물, 소듐하이알루로네이트, 녹차추출물, 크랜베리추출물, 병풀추출물, 아크릴레이트/C10-30알킬아크릴레이트크로스폴리머, 다이메티콘, 암모늄아크릴로일다이메틸타우레이트/브이피코폴리머, 포타슘하이드록사이드, 비에이치티, 부틸렌글라이콜, 글리세린, 포타슘솔베이트, 시트릭애씨드, 다이소듐이디티에이, 카프릴릴글라이콜, 에틸헥실글리세린, 1,2-헥산다이올, 향료, 벤질벤조에이트, 시트로넬올, 알파-아이소메틸아이오논, 헥실신나몰, 부틸페닐메틸프로피오날, 리모넨, 하이드록시시트로넬알",


"caution": "1. 화장품 사용 시 또는 사용 후 직사광선에 의하여 사용부위가 붉은 반점, 부어오름 또는 가려움증 등의 이상 증상이나 부작용이 있는 경우 전문의 등과 상담할 것 2. 상처가 있는 부위 등에는 사용을 자제할 것 3. 보관 및 취급 시의 주의사항 가. 어린이의 손이 닿지 않는 곳에 보관할 것 나. 직사광선을 피해서 보관할 것"

},

{


"id": "12ed0baa-7aef-47a1-8634-c6f58cdc191d",


"name": "퓨어 블록 톤업 선 베이스",


"price": "8000",


"brand": "어퓨",


"image_url": "https://static.mynunc.com/ext/images/goods/top/20/04/03/01/BO00084461/0000004931.jpg",


"category": 5,


"site": 5,


"site_id": "BO00079236",


"link": "https://www.mynunc.com/product/goods/view-goods?goodsId=BO00079236&dspCateId=",


"site_category": "20000139",


"volume": "50",


"expiration_date": "발송일로부터 사용기한이 18개월 이상 남은 제품으로 발송",


"usage": "상품 상세 설명 참조",


"origin": "한국",


"ingredients": "정제수, 사이클로펜타실록산, 에칠헥실메톡시신나메이트, 부틸렌글라이콜, 글리세린, 징크옥사이드, 티타늄디옥사이드, 에칠헥실살리실레이트, 사이클로헥사실록산, 나이아신아마이드, 카프릴릴메치콘, 피이지-10디메치콘, 자몽추출물, 파파야열매수, 오렌지오일, 석류나무추출물, 수박추출물, 타히티바닐라추출물, 라임추출물, 사과나무꽃추출물, 서양자두씨추출물, 복숭아나무꽃추출물, 세틸피이지/피피지-10/1디메치콘, 디메치콘/비닐디메치콘크로스폴리머, 마그네슘설페이트, 디스테아디모늄헥토라이트, 소르비탄이소스테아레이트, 알루미늄하이드록사이드, 스테아릭애씨드, 디메치콘, 글리세릴카프릴레이트, 카프릴릴글라이콜, 아데노신, 트리에톡시카프릴릴실란, 프로필렌글라이콜, 시트룰린, 탤크, 페녹시에탄올, 소듐벤조에이트, 포타슘소르베이트, 향료, 적색산화철 (CI 77491), 황색산화철 (CI 77492), 리모넨, 부틸페닐메틸프로피오날",


"caution": " 1. 화장품을 사용하여 다음과 같은 이상이 있는 경우에는 사용을 중지하여야 하며, 계속 사용하면 증상이 악화되므로 피부과 전문의 등에게 상담할 것 가. 사용 중 붉은 반점, 부어오름, 가려움증, 자극 등의 이상이 있는 경우 나. 적용 부위가 직사광선에 의하여 위와 같은 이상이 있는 경우 2. 상처가 있는 부위, 습진 및 피부염 등의 이상이 있는 부위에는 사용을 하지 말 것 3. 보관 및 취급 시의 주의사항 가. 사용 후에는 반드시 마개를 닫아둘 것 나. 유아,소아의 손이 닿지 않는 곳에 보관할 것 다. 고온 또는 저온의 장소 및 직사광선이 닿는 곳에는 보관하지 말 것 4. 이 제품의 자외선차단지수는 「유럽(Cosmetics Europe」자외선차단지수 측정방법에 따라, 자외선A 차단 등급은 「일본(JCIA)」자외선A차단효과 측정방법에 따라 측정하였음"

},

{


"id": "c5029ade-7869-4e2e-a7ea-33d21abcb985",


"name": "퓨어 블록 내추럴 데일리 선크림[대용량]",


"price": "13000",


"brand": "어퓨",


"image_url": "https://static.mynunc.com/ext/images/goods/top/20/04/03/01/BO00084461/0000004931.jpg",


"category": 5,


"site": 5,


"site_id": "BO00079235",


"link": "https://www.mynunc.com/product/goods/view-goods?goodsId=BO00079235&dspCateId=",


"site_category": "20000139",


"volume": "100",


"expiration_date": "발송일로부터 사용기한이 18개월 이상 남은 제품으로 발송",


"usage": "상품 상세 설명 참조",


"origin": "한국",


"ingredients": "정제수, 에칠헥실메톡시신나메이트, 에칠헥실살리실레이트, 부틸렌글라이콜, 페닐벤즈이미다졸설포닉애씨드, 카프릴릭/카프릭트리글리세라이드, 부틸메톡시디벤조일메탄, 비스-에칠헥실옥시페놀메톡시페닐트리아진, 메칠메타크릴레이트크로스폴리머, 글리세릴스테아레이트, 라임꽃추출물, 세테아릴올리베이트, 해수, 복숭아나무꽃추출물, 세테아릴알코올, 나일론-12, 소르비탄올리베이트, 소듐하이드록사이드, 사과나무꽃추출물, 디메치콘, 폴리아크릴레이트-13, 판테놀, 폴리이소부텐, 피이지-100스테아레이트, 토코페릴아세테이트, 석류나무꽃추출물, 소르비탄스테아레이트, 쌀겨추출물, 아세로라추출물, 알로에베라잎추출물, 유칼립투스잎추출물, 다마스크장미꽃수, 양벚나무꽃추출물, 오렌지꽃추출물, 수박추출물, 소르비탄이소스테아레이트, 폴리소르베이트20,비에이치티, 디소듐이디티에이, 1,2-헥산디올, 에칠헥실글리세린, 카프릴릴글라이콜, 향료, 리모넨, 리날룰, 부틸페닐메틸프로피오날",


"caution": "1. 화장품을 사용하여 다음과 같은 이상이 있는 경우에는 사용을 중지하여야 하며, 계속 사용하면 증상이 악화되므로 피부과 전문의 등에게 상담할 것 가. 사용 중 붉은 반점, 부어오름, 가려움증, 자극 등의 이상이 있는 경우 나. 적용 부위가 직사광선에 의하여 위와 같은 이상이 있는 경우 2. 상처가 있는 부위, 습진 및 피부염 등의 이상이 있는 부위에는 사용을 하지 말 것 3. 보관 및 취급 시의 주의사항 가. 사용 후에는 반드시 마개를 닫아둘 것 나. 유아, 소아의 손이 닿지 않는 곳에 보관할 것 다. 고온 또는 저온의 장소 및 직사광선이 닿는 곳에는 보관하지 말 것 4. 이 제품의 자외선차단지수는 「기능성화장품심사에관한규정」에 따라, 자외선A 차단 등급은 「기능성화장품심사에관한규정」에 따라 측정하였음"

},

{


"id": "1e262a1b-46d8-4717-80bb-6c327a4b2481",


"name": "퓨어 블록 내추럴 워터프루프 선크림",


"price": "7800",


"brand": "어퓨",


"image_url": "https://static.mynunc.com/ext/images/goods/top/20/04/03/01/BO00084461/0000004931.jpg",


"category": 5,


"site": 5,


"site_id": "BO00079232",


"link": "https://www.mynunc.com/product/goods/view-goods?goodsId=BO00079232&dspCateId=",


"site_category": "20000139",


"volume": "50",


"expiration_date": "발송일로부터 사용기한이 18개월 이상 남은 제품으로 발송",


"usage": "상품 상세 설명 참조",


"origin": "한국",


"ingredients": "정제수, 사이클로펜타실록산, 징크옥사이드 (CI 77947), 에칠헥실메톡시신나메이트, 사이클로헥사실록산, 티타늄디옥사이드 (CI 77891), 에칠헥실살리실레이트, C12-15알킬벤조에이트, 글리세린, 옥토크릴렌, 소듐클로라이드, 알로에베라잎추출물, 오렌지오일, 석류나무추출물, 수박추출물, 타히티바닐라추출물, 라임추출물, 사과나무꽃추출물, 서양자두씨추출물, 복숭아나무꽃추출물, 세틸피이지/피피지-10/1디메치콘, 메칠메타크릴레이트크로스폴리머, 소르비탄이소스테아레이트, 알루미늄하이드록사이드, 스테아릭애씨드, 디스테아디모늄헥토라이트, 실리카디메칠실릴레이트, 카프릴릴글라이콜, 디메치콘, 에칠헥실글리세린, 디메치콘/비닐디메치콘크로스폴리머, 부틸렌글라이콜, 시트룰린, 디소듐이디티에이, 페녹시에탄올, 소듐벤조에이트, 포타슘소르베이트, 향료, 리모넨, 부틸페닐메틸프로피오날",


"caution": "1. 화장품을 사용하여 다음과 같은 이상이 있는 경우에는 사용을 중지하여야 하며, 계속 사용하면 증상이 악화되므로 피부과 전문의 등에게 상담할 것 가. 사용 중 붉은 반점, 부어오름, 가려움증, 자극 등의 이상이 있는 경우 나. 적용 부위가 직사광선에 의하여 위와 같은 이상이 있는 경우 2. 상처가 있는 부위, 습진 및 피부염 등의 이상이 있는 부위에는 사용을 하지 말 것 3. 보관 및 취급 시의 주의사항 가. 사용 후에는 반드시 마개를 닫아둘 것 나. 유아, 소아의 손이 닿지 않는 곳에 보관할 것 다. 고온 또는 저온의 장소 및 직사광선이 닿는 곳에는 보관하지 말 것 4. 이 제품의 자외선차단지수는「유럽(Cosmetics Europe)」 자외선차단지수 측정방법에 따라, 자외선A차단등급은「일본(JCIA)」자외선A차단효과 측정방법에 따라, 지속내수성은「유럽(Cosmetics Europe)」 지속내수성 측정방법에 따라 측정하였음."

},

{


"id": "cff3d2f8-f3c0-4857-8e63-a158c92fa99e",


"name": "퓨어 블록 내추럴 데일리 선크림",


"price": "7800",


"brand": "어퓨",


"image_url": "https://static.mynunc.com/ext/images/goods/top/20/04/03/01/BO00084461/0000004931.jpg",


"category": 5,


"site": 5,


"site_id": "BO00079231",


"link": "https://www.mynunc.com/product/goods/view-goods?goodsId=BO00079231&dspCateId=",


"site_category": "20000139",


"volume": "50",


"expiration_date": "발송일로부터 사용기한이 18개월 이상 남은 제품으로 발송",


"usage": "상품 상세 설명 참조",


"origin": "한국",


"ingredients": "정제수, 에칠헥실메톡시신나메이트, 에칠헥실살리실레이트, 부틸렌글라이콜, 페닐벤즈이미다졸설포닉애씨드, 카프릴릭/카프릭트리글리세라이드, 부틸메톡시디벤조일메탄, 비스-에칠헥실옥시페놀메톡시페닐트리아진, 메칠메타크릴레이트크로스폴리머, 글리세릴스테아레이트, 라임꽃추출물, 세테아릴올리베이트, 해수, 복숭아나무꽃추출물, 세테아릴알코올, 나일론-12,소르비탄올리베이트, 소듐하이드록사이드, 사과나무꽃추출물, 디메치콘, 폴리아크릴레이트-13, 판테놀, 폴리이소부텐, 피이지-100스테아레이트, 토코페릴아세테이트, 석류나무꽃추출물, 소르비탄스테아레이트, 쌀겨추출물, 아세로라추출물, 알로에베라잎추출물, 유칼립투스잎추출물, 다마스크장미꽃수, 양벚나무꽃추출물, 오렌지꽃추출물, 수박추출물, 소르비탄이소스테아레이트, 폴리소르베이트20, 비에이치티, 디소듐이디티에이, 1,2-헥산디올, 에칠헥실글리세린, 카프릴릴글라이콜, 향료, 리모넨, 리날룰, 부틸페닐메틸프로피오날",


"caution": "1. 화장품을 사용하여 다음과 같은 이상이 있는 경우에는 사용을 중지하여야 하며, 계속 사용하면 증상이 악화되므로 피부과 전문의 등에게 상담할 것 가. 사용 중 붉은 반점, 부어오름, 가려움증, 자극 등의 이상이 있는 경우 나. 적용 부위가 직사광선에 의하여 위와 같은 이상이 있는 경우 2. 상처가 있는 부위, 습진 및 피부염 등의 이상이 있는 부위에는 사용을 하지 말 것 3. 보관 및 취급 시의 주의사항 가. 사용 후에는 반드시 마개를 닫아둘 것 나. 유아, 소아의 손이 닿지 않는 곳에 보관할 것 다. 고온 또는 저온의 장소 및 직사광선이 닿는 곳에는 보관하지 말 것 4. 이 제품의 자외선차단지수는 「기능성화장품심사에관한규정」에 따라, 자외선A 차단 등급은 「기능성화장품심사에관한규정」에 따라 측정하였음"

},

{


"id": "05d0cbff-89d1-4cc5-a51c-ddefab204b0a",


"name": "[미샤] 올 어라운드 세이프 블록 소프트피니쉬 선 밀크 70ml",


"price": "19800",


"brand": "미샤",


"image_url": "https://static.mynunc.com/ext/images/goods/top/20/04/03/01/BO00084461/0000004931.jpg",


"category": 5,


"site": 5,


"site_id": "BO00079141",


"link": "https://www.mynunc.com/product/goods/view-goods?goodsId=BO00079141&dspCateId=",


"site_category": "20000139",


"volume": "70",


"expiration_date": "발송일로부터 사용기한이 18개월 이상 남은 제품으로 발송",


"usage": "상품 상세 설명 참조",


"origin": "한국",


"ingredients": "옐로우체이스트위드추출물, 사이클로펜타실록세인, 실리카, 징크옥사이드, 다이프로필렌글라이콜, 라우릴피이지-10트리스(트라이메틸실록시)실릴에틸다이메티콘, 아이소프로필팔미테이트, 에칠헥실살리실레이트, 에칠헥실메톡시신나메이트, 카프릴릴메티콘, 티타늄디옥사이드, 변성알코올, C12-15알킬벤조에이트, 아크릴레이트/다이메티콘코폴리머, 브이피/헥사데센코폴리머, 리모니아 아키디시마추출물, 생열귀나무싹추출물, 데저트샌드버베나잎추출물, 알로에베라잎추출물, 키나나무껍질추출물, 구아바잎추출물, 바위돌꽃뿌리추출물, 바이오사카라이드검-4, 비스-에칠헥실옥시페놀메톡시페닐트리아진, 마그네슘설페이트, 다이메티콘/비닐다이메티콘크로스폴리머, 다이메티콘, 디에칠아미노하이드록시벤조일헥실벤조에이트, 쿼터늄-18벤토나이트, 알루미늄하이드록사이드, 스테아릭애씨드, 하이드로젠다이메티콘, 정제수, 실리카다이메틸실릴레이트, 소듐벤조에이트, 토코페릴아세테이트, 포타슘솔베이트, 폴리하이드록시스테아릭애씨드, 아이소프로필미리스테이트, 아이소스테아릭애씨드, 레시틴, 에틸헥실팔미테이트, 폴리글리세릴-3폴리리시놀리에이트, 다이소듐이디티에이, 페녹시에탄올, 적색산화철, 황색산화철, 헥실신나몰, 벤질살리실레이트",


"caution": "1) 화장품 사용 시 또는 사용 후 직사광선에 의하여 사용부위가 붉은 반점, 부어오름 또는 가려움증 등의 이상 증상이나 부작용이 있는 경우 전문의 등과 상담할 것 2) 상처가 있는 부위 등에는 사용을 자제할 것 3) 보관 및 취급 시의 주의사항 가) 어린이의 손이 닿지 않는 곳에 보관할 것 나) 직사광선을 피해서 보관할 것."

},

{


"id": "f7a276d8-a421-4c22-9d10-164ae45b5b25",


"name": "[미샤] 올 어라운드 세이프 블록 워터프루프 선 밀크 70ml ",


"price": "21800",


"brand": "미샤",


"image_url": "https://static.mynunc.com/ext/images/goods/top/20/04/03/01/BO00084461/0000004931.jpg",


"category": 5,


"site": 5,


"site_id": "BO00079139",


"link": "https://www.mynunc.com/product/goods/view-goods?goodsId=BO00079139&dspCateId=",


"site_category": "20000139",


"volume": "70",


"expiration_date": "발송일로부터 사용기한이 18개월 이상 남은 제품으로 발송",


"usage": "상품 상세 설명 참조",


"origin": "한국",


"ingredients": "옐로우체이스트위드추출물, 사이클로펜타실록세인, 호모살레이트, 실리카, 에칠헥실살리실레이트, 티타늄디옥사이드, 라우릴피이지-10트리스(트라이메틸실록시)실릴에틸다이메티콘, 디에칠아미노하이드록시벤조일헥실벤조에이트, 글리세린, C12-15알킬벤조에이트, 변성알코올, 비스-에칠헥실옥시페놀메톡시페닐트리아진, 아이소프로필팔미테이트, 알로에베라잎추출물, 구아바잎추출물, 데저트샌드버베나잎추출물, 키나나무껍질추출물, 바위돌꽃뿌리추출물, 유칼립투스잎추출물, 정제수, 부틸렌글라이콜, 다이메티콘, 마그네슘설페이트, 알루미늄하이드록사이드, 스테아릭애씨드, 쿼터늄-18벤토나이트, 피이지-10다이메티콘, 다이메티콘/비닐다이메티콘크로스폴리머, 트라이에톡시카프릴릴실레인, 아크릴레이트/다이메티콘코폴리머, 실리카다이메틸실릴레이트, 소듐벤조에이트, 토코페릴아세테이트, 포타슘솔베이트, 브이피/헥사데센코폴리머, 다이소듐이디티에이, 페녹시에탄올, 리날룰, 벤질살리실레이트, 리모넨, 제라니올, 헥실신나몰",


"caution": "1) 화장품 사용 시 또는 사용 후 직사광선에 의하여 사용부위가 붉은 반점, 부어오름 또는 가려움증 등의 이상 증상이나 부작용이 있는 경우 전문의 등과 상담할 것 2) 상처가 있는 부위 등에는 사용을 자제할 것 3) 보관 및 취급 시의 주의사항 가) 어린이의 손이 닿지 않는 곳에 보관할 것 나) 직사광선을 피해서 보관할 것."

},

{


"id": "7f4758a5-ca2e-42d0-9afb-b20dfadb27a7",


"name": "[미샤] 올 어라운드 세이프 블록 에센스 선 밀크 70ml",


"price": "19800",


"brand": "미샤",


"image_url": "https://static.mynunc.com/ext/images/goods/top/20/04/03/01/BO00084461/0000004931.jpg",


"category": 5,


"site": 5,


"site_id": "BO00079137",


"link": "https://www.mynunc.com/product/goods/view-goods?goodsId=BO00079137&dspCateId=",


"site_category": "20000139",


"volume": "70",


"expiration_date": "발송일로부터 사용기한이 18개월 이상 남은 제품으로 발송",


"usage": "상품 상세 설명 참조",


"origin": "한국",


"ingredients": "옐로우체이스트위드추출물, 에칠헥실메톡시신나메이트, 변성알코올, 옥토크릴렌, 에칠헥실살리실레이트, 부틸메톡시디벤조일메탄, 부틸렌글라이콜, 메틸메타크릴레이트크로스폴리머, 실리카, 비스-에칠헥실옥시페놀메톡시페닐트리아진, 접시꽃뿌리추출물, 생열귀나무싹추출물, 쇠비름추출물, 연꽃추출물, 데저트샌드버베나잎추출물, 알로에베라잎추출물, 키나나무껍질추출물, 바위돌꽃뿌리추출물, 구아바잎추출물, 리모니아 아키디시마추출물, 감국꽃추출물, 녹차추출물, 칡뿌리추출물, 뽕나무열매추출물, 육계나무껍질추출물, 감나무잎추출물, 쑥잎추출물, 동백나무꽃추출물, 매실나무꽃추출물, 포트마리골드꽃수, 센티드제라늄꽃수, 살비아수, 바이오사카라이드검-4, 다이메티콘, 나일론-12, 아크릴레이트/C10-30알킬아크릴레이트크로스폴리머, 비에이치티, 소듐하이드록사이드, 브이피/헥사데센코폴리머, 베타인, 카프릴릴메티콘, 사이클로펜타실록세인, 비스-피이지/피피지-20/5피이지/피피지-20/5다이메티콘, 메톡시피이지/피피지-25/다이메티콘, 아크릴레이트/다이메티콘코폴리머, 카프릴릭/카프릭트라이글리세라이드, 다이소듐이디티에이, 카프릴릴글라이콜, 에틸헥실글리세린, 1,2-헥산다이올, 리날룰, 리모넨, 벤질살리실레이트, 제라니올, 헥실신나몰",


"caution": "1) 화장품 사용 시 또는 사용 후 직사광선에 의하여 사용부위가 붉은 반점, 부어오름 또는 가려움증 등의 이상 증상이나 부작용이 있는 경우 전문의 등과 상담할 것 2) 상처가 있는 부위 등에는 사용을 자제할 것 3) 보관 및 취급 시의 주의사항 가) 어린이의 손이 닿지 않는 곳에 보관할 것 나) 직사광선을 피해서 보관할 것."

},

{


"id": "4bddbbeb-fddc-4491-899f-0cb55704a544",


"name": "[미샤] 올 어라운드 세이프 블록 벨벳 피니쉬 선 밀크 70ml",


"price": "21800",


"brand": "미샤",


"image_url": "https://static.mynunc.com/ext/images/goods/top/20/04/03/01/BO00084461/0000004931.jpg",


"category": 5,


"site": 5,


"site_id": "BO00079136",


"link": "https://www.mynunc.com/product/goods/view-goods?goodsId=BO00079136&dspCateId=",


"site_category": "20000139",


"volume": "70",


"expiration_date": "발송일로부터 사용기한이 18개월 이상 남은 제품으로 발송",


"usage": "상품 상세 설명 참조",


"origin": "한국",


"ingredients": "옐로우체이스트위드추출물, 사이클로펜타실록세인, 호모살레이트, 실리카, 티타늄디옥사이드, 에칠헥실살리실레이트, 변성알코올, 다이프로필렌글라이콜, 라우릴피이지-10트리스(트라이메틸실록시)실릴에틸다이메티콘, 아이소프로필팔미테이트, 카프릴릴메티콘, 디에칠아미노하이드록시벤조일헥실벤조에이트, C12-15알킬벤조에이트, 비스-에칠헥실옥시페놀메톡시페닐트리아진, 데저트샌드버베나잎추출물, 구아바잎추출물, 알로에베라잎추출물, 키나나무껍질추출물, 바위돌꽃뿌리추출물, 다마스크장미꽃수, 에델바이스꽃/잎추출물, 정제수, 부틸렌글라이콜, 바이오사카라이드검-4, 알루미늄하이드록사이드, 마그네슘설페이트, 스테아릭애씨드, 쿼터늄-18벤토나이트, 다이메티콘/비닐다이메티콘크로스폴리머, 다이메티콘, 실리카다이메틸실릴레이트, 소듐벤조에이트, 토코페릴아세테이트, 포타슘솔베이트, 폴리하이드록시스테아릭애씨드, 아이소스테아릭애씨드, 레시틴, 에틸헥실팔미테이트, 아이소프로필미리스테이트, 폴리글리세릴-3폴리리시놀리에이트, 브이피/헥사데센코폴리머, 아크릴레이트/다이메티콘코폴리머, 다이소듐이디티에이, 페녹시에탄올, 카프릴릴글라이콜, 에틸헥실글리세린, 적색산화철, 황색산화철, 흑색산화철, 벤질살리실레이트, 부틸페닐메틸프로피오날, 벤질벤조에이트, 리날룰, 시트로넬올, 알파-아이소메틸아이오논, 제라니올, 리모넨",


"caution": "1) 화장품 사용 시 또는 사용 후 직사광선에 의하여 사용부위가 붉은 반점, 부어오름 또는 가려움증 등의 이상 증상이나 부작용이 있는 경우 전문의 등과 상담할 것 2) 상처가 있는 부위 등에는 사용을 자제할 것 3) 보관 및 취급 시의 주의사항 가) 어린이의 손이 닿지 않는 곳에 보관할 것 나) 직사광선을 피해서 보관할 것."

},

{


"id": "28d166d1-6cc6-42cd-979b-0fceaa414fea",


"name": "[미샤] 올 어라운드 세이프 블록 에센스 선 50ml",


"price": "9800",


"brand": "미샤",


"image_url": "https://static.mynunc.com/ext/images/goods/top/20/04/03/01/BO00084461/0000004931.jpg",


"category": 5,


"site": 5,


"site_id": "BO00079124",


"link": "https://www.mynunc.com/product/goods/view-goods?goodsId=BO00079124&dspCateId=",


"site_category": "20000139",


"volume": "50",


"expiration_date": "발송일로부터 사용기한이 18개월 이상 남은 제품으로 발송",


"usage": "상품 상세 설명 참조",


"origin": "한국",


"ingredients": "정제수, 에칠헥실메톡시신나메이트, 에칠헥실살리실레이트, 페닐벤즈이미다졸설포닉애씨드, 부틸렌글라이콜, 디에칠아미노하이드록시벤조일헥실벤조에이트, 메틸메타크릴레이트크로스폴리머, C12-15알킬벤조에이트, 세테아릴알코올, 비스-에칠헥실옥시페놀메톡시페닐트리아진, 글리세릴스테아레이트, 세테아릴올리베이트, 사이클로펜타실록세인, 아크릴레이트/다이메티콘코폴리머, 브이피/헥사데센코폴리머, 생열귀나무싹추출물, 연꽃추출물, 감국꽃추출물, 녹차추출물, 쑥잎추출물, 감나무잎추출물, 육계나무껍질추출물, 뽕나무열매추출물, 칡뿌리추출물, 알로에베라잎즙, 스페인감초뿌리추출물, 뽕나무뿌리추출물, 오이열매추출물, 쇠비름추출물, 버지니아풍년화수, 리모니아 아키디시마추출물, 수레국화꽃수, 타임잎수, 에버라스팅꽃수, 솔비탄올리베이트, 소듐하이드록사이드, 폴리솔베이트60, 다이메티콘, 폴리아크릴레이트-13, 피이지-100스테아레이트, 폴리아이소부텐, 솔비탄세스퀴올리에이트, 비에이치티, 솔비탄아이소스테아레이트, 폴리솔베이트20, 판테놀, 다이소듐이디티에이, 카프릴릴글라이콜, 에틸헥실글리세린, 1,2-헥산다이올, 리날룰, 부틸페닐메틸프로피오날, 리모넨, 시트로넬올",


"caution": "1) 화장품 사용 시 또는 사용 후 직사광선에 의하여 사용부위가 붉은 반점, 부어오름 또는 가려움증 등의 이상 증상이나 부작용이 있는 경우 전문의 등과 상담할 것 2) 상처가 있는 부위 등에는 사용을 자제할 것 3) 보관 및 취급 시의 주의사항 가) 어린이의 손이 닿지 않는 곳에 보관할 것 나) 직사광선을 피해서 보관할 것."

},

{


"id": "d10a4c1f-2eaa-4480-a236-6ad2ae1d0d10",


"name": "[미샤] 올 어라운드 세이프 블록 데일리 선 50ml",


"price": "11800",


"brand": "미샤",


"image_url": "https://static.mynunc.com/ext/images/goods/top/20/04/03/01/BO00084461/0000004931.jpg",


"category": 5,


"site": 5,


"site_id": "BO00079123",


"link": "https://www.mynunc.com/product/goods/view-goods?goodsId=BO00079123&dspCateId=",


"site_category": "20000139",


"volume": "50",


"expiration_date": "발송일로부터 사용기한이 18개월 이상 남은 제품으로 발송",


"usage": "상품 상세 설명 참조",


"origin": "한국",


"ingredients": "정제수, 호모살레이트, 실리카, 프로판다이올, 에칠헥실살리실레이트, 티타늄디옥사이드, 다이프로필렌글라이콜, C12-15알킬벤조에이트, 디에칠아미노하이드록시벤조일헥실벤조에이트, 다이메티콘, 변성알코올, 폴리솔베이트60, 포타슘세틸포스페이트, 부틸렌글라이콜, 비스-에칠헥실옥시페놀메톡시페닐트리아진, 녹차추출물, 감국꽃추출물, 육계나무껍질추출물, 쑥잎추출물, 감나무잎추출물, 뽕나무열매추출물, 칡뿌리추출물, 에델바이스꽃/잎추출물, 알로에베라잎추출물, 포트마리골드꽃추출물, 해바라기씨추출물, 캐모마일꽃추출물, 수레국화꽃수, 에버라스팅꽃수, 타임잎수, 미리스틱애씨드, 소듐벤조에이트, 시트릭애씨드, 사이클로펜타실록세인, 아크릴레이트/다이메티콘코폴리머, 글리세릴스테아레이트, 소듐아크릴레이트/소듐아크릴로일다이메틸타우레이트코폴리머, 브이피/헥사데센코폴리머, 세테아릴올리베이트, 스테아릭애씨드, 알루미늄하이드록사이드, 아이소헥사데칸, 솔비탄올리베이트, 세테아릴알코올, 솔비탄스테아레이트, 폴리솔베이트80, 팔미틱애씨드, 카보머, 트로메타민, 토코페릴아세테이트, 잔탄검, 솔비탄올리에이트, 포타슘하이드록사이드, 다이소듐이디티에이, 페녹시에탄올, 카프릴릴글라이콜, 에틸헥실글리세린, 1,2-헥산다이올, 향료, 벤질벤조에이트, 부틸페닐메틸프로피오날, 리모넨",


"caution": "1) 화장품 사용 시 또는 사용 후 직사광선에 의하여 사용부위가 붉은 반점, 부어오름 또는 가려움증 등의 이상 증상이나 부작용이 있는 경우 전문의 등과 상담할 것 2) 상처가 있는 부위 등에는 사용을 자제할 것 3) 보관 및 취급 시의 주의사항 가) 어린이의 손이 닿지 않는 곳에 보관할 것 나) 직사광선을 피해서 보관할 것."

},

{


"id": "06b1b9ce-ed2f-4eb3-9a78-af29528de781",


"name": "시카티브 선크림(아연)",


"price": "9500",


"brand": "어퓨",


"image_url": "https://static.mynunc.com/ext/images/goods/top/20/04/03/01/BO00084461/0000004931.jpg",


"category": 5,


"site": 5,


"site_id": "BO00078964",


"link": "https://www.mynunc.com/product/goods/view-goods?goodsId=BO00078964&dspCateId=",


"site_category": "20000139",


"volume": "40g",


"expiration_date": "발송일로부터 사용기한이 18개월 이상 남은 제품으로 발송",


"usage": "상품 상세 설명 참조",


"origin": "한국",


"ingredients": "병풀추출물, 사이클로펜타실록산, 징크옥사이드, 디프로필렌글라이콜, 디카프릴릴카보네이트, 피이지-10디메치콘, 디메치콘, 카프릴릴메치콘, 글리세린, 실리카, 소듐클로라이드, 사이클로헥사실록산, 하이드로젠디메치콘, 징크피씨에이, 미네랄워터, 부틸렌글라이콜, 펜틸렌글라이콜, 스쿠알란, 소르비탄올리베이트, 디스테아디모늄헥토라이트, 소르비탄세스퀴올리에이트, 디메치콘/비닐디메치콘크로스폴리머, 폴리하이드록시스테아릭애씨드, 쿼터늄-18벤토나이트, 토코페릴아세테이트, 에칠헥실팔미테이트, 이소프로필팔미테이트, 이소스테아릭애씨드, 레시틴, 폴리글리세릴-3폴리리시놀리에이트, 디소듐이디티에이, 페녹시에탄올, 카프릴릴글라이콜, 1,2-헥산디올, 향료",


"caution": "1. 화장품 사용 시 또는 사용 후 직사광선에 의하여 사용부위가 붉은 반점, 부어오름 또는 가려움증 등의 이상 증상이나 부작용이 있는 경우 전문의 등과 상담할 것 2. 상처가 있는 부위 등에는 사용을 자제할 것 3. 보관 및 취급 시의 주의사항 가. 어린이의 손이 닿지 않는 곳에 보관할 것 나. 직사광선을 피해서 보관할 것"

}
]